Workbook

Sheet Financials>
B2: Legend
B3: Hardcoded
B4: Formula
B5: Intersheet Links
B6: Intrasheet Links
B8: Note -
B9: All Hardcoded numbers are taken from the Company's 10K, 8K reports and trusted websites

Sheet Revenue
A2: # | B2: Particulars | C2: Unit | D2: Historical | H2: Forecast
D3: 2021 | E3: =D3+1 -> 2022 | F3: =E3+1 -> 2023 | G3: =F3+1 -> 2024 | H3: =G3+1 -> 2025 | I3: =H3+1 -> 2026 | J3: =I3+1 -> 2027 | K3: =J3+1 -> 2028 | L3: =K3+1 -> 2029
B5: Europe, Middle East & Africa | C5: $ | D5: 7193 | E5: 7523 | F5: 8078 | G5: 8122 | H5: =G5*(1+H8) -> 9391.9357 | I5: =H5*(1+I8) -> 10753.727 | J5: =I5*(1+J8) -> 12190.791 | K5: =J5*(1+K8) -> 13681.388 | L5: =K5*(1+L8) -> 15323.154
B6: Growth Rate % | E6: =E5/D5-1 -> 0.045877937 | F6: =F5/E5-1 -> 0.07377376 | G6: =G5/F5-1 -> 0.0054468928
B7: Add/Less: Inorganic growth 1 | D7: -0.01 | E7: 0.124 | F7: 0.12 | G7: 0.16
B8: Organic Growth % | E8: =E6+E7 -> 0.16987794 | F8: =F6+F7 -> 0.19377376 | G8: =G6+G7 -> 0.16544689 | H8: =G8-(($G$8-$L$8)/5) -> 0.15635751 | I8: =H8-(($G$8-$L$8)/4) -> 0.14499579 | J8: =I8-(($G$8-$L$8)/4) -> 0.13363407 | K8: =J8-(($G$8-$L$8)/4) -> 0.12227234 | L8: 0.12
B10: Latin America | D10: 4143 | E10: 4910 | F10: 5830 | G10: 6459 | H10: =G10*(1+H13) -> 7933.6684 | I10: =H10*(1+I13) -> 9589.6958 | J10: =I10*(1+J13) -> 11403.645 | K10: =J10*(1+K13) -> 13337.453 | L10: =K10*(1+L13) -> 15338.071
B11: Growth Rate % | E11: =E10/D10-1 -> 0.18513155 | F11: =F10/E10-1 -> 0.18737271 | G11: =G10/F10-1 -> 0.10789022
B12: Add/Less: Inorganic growth | E12: 0.06 | F12: 0.03 | G12: 0.14
B13: Organic Growth % | E13: =E11+E12 -> 0.24513155 | F13: =F11+F12 -> 0.21737271 | G13: =G11+G12 -> 0.24789022 | H13: =G13-(($G$13-$L$13)/5) -> 0.22831218 | I13: =H13-(($G$13-$L$13)/5) -> 0.20873413 | J13: =I13-(($G$13-$L$13)/5) -> 0.18915609 | K13: =J13-(($G$13-$L$13)/5) -> 0.16957804 | L13: 0.15
B15: North America | D15: 13190 | E15: 15674 | F15: 16774 | G15: 18649 | H15: =G15*(1+H18) -> 20577.756 | I15: =H15*(1+I18) -> 22534.044 | J15: =I15*(1+J18) -> 24488.017 | K15: =J15*(1+K18) -> 26406.801 | L15: =K15*(1+L18) -> 28255.277
B16: Growth Rate % | E16: =E15/D15-1 -> 0.18832449 | F16: =F15/E15-1 -> 0.070179916 | G16: =G15/F15-1 -> 0.11178014
B17: Add/Less: Inorganic growth | E17: -0.06 | F17: 0 | G17: 0
B18: Organic Growth % | E18: =E16+E17 -> 0.12832449 | F18: =F16+F17 -> 0.070179916 | G18: =G16+G17 -> 0.11178014 | H18: =G18-(($G$18-$L$18)/5) -> 0.10342411 | I18: =H18-(($G$18-$L$18)/5) -> 0.095068082 | J18: =I18-(($G$18-$L$18)/5) -> 0.086712054 | K18: =J18-(($G$18-$L$18)/5) -> 0.078356027 | L18: 0.07
B20: Asia Pacific | D20: 5291 | E20: 5445 | F20: 5455 | G20: 5546 | H20: =G20*(1+H23) -> 5830.7624 | I20: =H20*(1+I23) -> 6157.3386 | J20: =I20*(1+J23) -> 6530.9214 | K20: =J20*(1+K23) -> 6957.6282 | L20: =K20*(1+L23) -> 7444.6622
B21: Growth Rate % | E21: =E20/D20-1 -> 0.029106029 | F21: =F20/E20-1 -> 0.0018365473 | G21: =G20/F20-1 -> 0.016681943
B22: Add/Less: Inorganic growth | E22: 0.08 | F22: 0.04 | G22: 0.03
B23: Organic Growth % | E23: =E21+E22 -> 0.10910603 | F23: =F21+F22 -> 0.041836547 | G23: =G21+G22 -> 0.046681943 | H23: =G23-(($G$23-$L$23)/5) -> 0.051345555 | I23: =H23-(($G$23-$L$23)/5) -> 0.056009166 | J23: =I23-(($G$23-$L$23)/5) -> 0.060672777 | K23: =J23-(($G$23-$L$23)/5) -> 0.065336389 | L23: 0.07
B25: Global Ventures | D25: 2805 | E25: 2843 | F25: 3064 | G25: 3129 | H25: =G25*(1+H28) -> 3163.3291 | I25: =H25*(1+I28) -> 3228.9001 | J25: =I25*(1+J28) -> 3327.3352 | K25: =J25*(1+K28) -> 3461.2365 | L25: =K25*(1+L28) -> 3634.2983
B26: Growth Rate % | E26: =E25/D25-1 -> 0.013547237 | F26: =F25/E25-1 -> 0.077734787 | G26: =G25/F25-1 -> 0.021214099
B27: Add/Less: Inorganic growth | E27: 0.12 | F27: 0 | G27: -0.02
B28: Organic Growth % | E28: =E26+E27 -> 0.13354724 | F28: =F26+F27 -> 0.077734787 | G28: =G26+G27 -> 0.0012140992 | H28: =G28-(($G$28-$L$28)/5) -> 0.010971279 | I28: =H28-(($G$28-$L$28)/5) -> 0.02072846 | J28: =I28-(($G$28-$L$28)/5) -> 0.03048564 | K28: =J28-(($G$28-$L$28)/5) -> 0.04024282 | L28: 0.05
B30: Bottling Investments | D30: 7203 | E30: 7891 | F30: 7860 | G30: 6223 | H30: =G30*(1+H33) -> 6022.4483 | I30: =H30*(1+I33) -> 5571.9175 | J30: =I30*(1+J33) -> 5023.4443 | K30: =J30*(1+K33) -> 4679.3864 | L30: =K30*(1+L33) -> 4302.3303
B31: Growth Rate % | E31: =E30/D30-1 -> 0.095515757 | F31: =F30/E30-1 -> -0.0039285262 | G31: =G30/F30-1 -> -0.20826972
B32: Add/Less: Inorganic growth (only fx) 2 | G32: 0.02
B33: Organic Growth % 3 | E33: =E31+E32 -> 0.095515757 | F33: =F31+F32 -> -0.0039285262 | G33: =G31+G32 -> -0.18826972 | H33: =AVERAGE(E33:G33) -> -0.032227496 | I33: =AVERAGE(F33:H33) -> -0.074808581 | J33: =AVERAGE(G33:I33) -> -0.098435266 | K33: =AVERAGE(H33:J33) -> -0.068490448 | L33: =AVERAGE(I33:K33) -> -0.080578098 | M33: 4
B35: Corporate | D35: 85 | E35: 94 | F35: 126 | G35: 97 | H35: =G35*(1+H38) -> 103.98882 | I35: =H35*(1+I38) -> 110.30845 | J35: =I35*(1+J38) -> 106.72942 | K35: =J35*(1+K38) -> 110.30046 | L35: =K35*(1+L38) -> 112.57211
B36: Growth Rate % | E36: =E35/D35-1 -> 0.10588235 | F36: =F35/E35-1 -> 0.34042553 | G36: =G35/F35-1 -> -0.23015873
B37: Add/Less: Inorganic growth | E37: 0 | F37: 0 | G37: 0
B38: Organic Growth % | E38: =E36+E37 -> 0.10588235 | F38: =F36+F37 -> 0.34042553 | G38: =G36+G37 -> -0.23015873 | H38: =AVERAGE(E38:G38) -> 0.072049718 | I38: =AVERAGE(F38:H38) -> 0.060772173 | J38: =AVERAGE(G38:I38) -> -0.032445613 | K38: =AVERAGE(H38:J38) -> 0.03345876 | L38: =AVERAGE(I38:K38) -> 0.020595107
B40: Total Revenue before Eliminations | D40: =SUM(D5,D10,D15,D20,D25,D30,D35) -> 39910 | E40: =SUM(E5,E10,E15,E20,E25,E30,E35) -> 44380 | F40: =SUM(F5,F10,F15,F20,F25,F30,F35) -> 47187 | G40: =SUM(G5,G10,G15,G20,G25,G30,G35) -> 48225 | H40: =SUM(H5,H10,H15,H20,H25,H30,H35) -> 53023.889 | I40: =SUM(I5,I10,I15,I20,I25,I30,I35) -> 57945.931 | J40: =SUM(J5,J10,J15,J20,J25,J30,J35) -> 63070.884 | K40: =SUM(K5,K10,K15,K20,K25,K30,K35) -> 68634.193 | L40: =SUM(L5,L10,L15,L20,L25,L30,L35) -> 74410.365
B42: Eliminations | D42: -1255 | E42: -1376 | F42: -1433 | G42: -1164 | H42: =-H40*H43 -> -1511.3638 | I42: =-I40*I43 -> -1651.6589 | J42: =-J40*J43 -> -1797.7378 | K42: =-K40*K43 -> -1956.3113 | L42: =-L40*L43 -> -2120.9521
B43: Eliminations as a % of Revenue before Eliminations | D43: =-D42/D40 -> 0.031445753 | E43: =-E42/E40 -> 0.031004957 | F43: =-F42/F40 -> 0.030368534 | G43: =-G42/G40 -> 0.024136858 | H43: =AVERAGE($E$43:$G$43) -> 0.02850345 | I43: =AVERAGE($E$43:$G$43) -> 0.02850345 | J43: =AVERAGE($E$43:$G$43) -> 0.02850345 | K43: =AVERAGE($E$43:$G$43) -> 0.02850345 | L43: =AVERAGE($E$43:$G$43) -> 0.02850345
A45: # | B45: Total Consolidated Revenue | D45: =SUM(D5,D10,D15,D20,D25,D30,D35,D42) -> 38655 | E45: =SUM(E5,E10,E15,E20,E25,E30,E35,E42) -> 43004 | F45: =SUM(F5,F10,F15,F20,F25,F30,F35,F42) -> 45754 | G45: =SUM(G5,G10,G15,G20,G25,G30,G35,G42) -> 47061 | H45: =SUM(H5,H10,H15,H20,H25,H30,H35,H42) -> 51512.525 | I45: =SUM(I5,I10,I15,I20,I25,I30,I35,I42) -> 56294.272 | J45: =SUM(J5,J10,J15,J20,J25,J30,J35,J42) -> 61273.146 | K45: =SUM(K5,K10,K15,K20,K25,K30,K35,K42) -> 66677.882 | L45: =SUM(L5,L10,L15,L20,L25,L30,L35,L42) -> 72289.413
B47: Notes -
B48: 1. Inorganic growth refers to the growth of revenue of the segment contributed by factors such as; forex currency fluctuations, restructuring activities in the form of acquisitions and divestments
B49: 2. Acquisitions and divestments factor is excluded in the inorganic growth adjustment for bottling investments segment due to historical data showing Coca-Cola's strategy of being asset-light in this segment by adopting a franchise model where bottling of their products is undertaken by bottling partners
B50: 3. In addition to the above note, the operating assumption is that Coca-Cola will further divest in this segment to reduce CapEx and focus on its brand value and hence the revenue from their own bottling investments will reduce in the forecasted years
B51: 4. %Figures which are more volatile/uncertain in terms of their historical changes are forecasted by applying a moving average in this financial model

Sheet P&L
A3: # | B3: Particulars | C3: Unit | D3: Historical | H3: Forecast
D4: 2021 | E4: =D4+1 -> 2022 | F4: =E4+1 -> 2023 | G4: =F4+1 -> 2024 | H4: =G4+1 -> 2025 | I4: =H4+1 -> 2026 | J4: =I4+1 -> 2027 | K4: =J4+1 -> 2028 | L4: =K4+1 -> 2029
B6: Net Operating Revenues | C6: $ | D6: =Revenue!D45 -> 38655 | E6: =Revenue!E45 -> 43004 | F6: =Revenue!F45 -> 45754 | G6: =Revenue!G45 -> 47061 | H6: =Revenue!H45 -> 51512.525 | I6: =Revenue!I45 -> 56294.272 | J6: =Revenue!J45 -> 61273.146 | K6: =Revenue!K45 -> 66677.882 | L6: =Revenue!L45 -> 72289.413
B7: Add/Less: Extraordinary Items 1 | D7: 3 | E7: 42 | F7: 30 | G7: -164 | H7: 0 | I7: 0 | J7: 0 | K7: 0 | L7: 0
B8: Normalised Revenue | D8: =SUM(D6:D7) -> 38658 | E8: =SUM(E6:E7) -> 43046 | F8: =SUM(F6:F7) -> 45784 | G8: =SUM(G6:G7) -> 46897 | H8: =SUM(H6:H7) -> 51512.525 | I8: =SUM(I6:I7) -> 56294.272 | J8: =SUM(J6:J7) -> 61273.146 | K8: =SUM(K6:K7) -> 66677.882 | L8: =SUM(L6:L7) -> 72289.413
B10: COGS | D10: 15357 | E10: 18000 | F10: 18520 | G10: 18324
B11: Add/Less: Extraordinary Items | D11: 53 | E11: -183 | F11: -55 | G11: -70
B12: Normalised COGS | D12: =SUM(D10:D11) -> 15410 | E12: =SUM(E10:E11) -> 17817 | F12: =SUM(F10:F11) -> 18465 | G12: =SUM(G10:G11) -> 18254 | H12: =H8-H13 -> 20670.337 | I12: =I8-I13 -> 22589.1 | J12: =J8-J13 -> 24586.963 | K12: =K8-K13 -> 26755.712 | L12: =L8-L13 -> 29007.441
B13: Normalised Gross Profit | D13: =D8-D12 -> 23248 | E13: =E8-E12 -> 25229 | F13: =F8-F12 -> 27319 | G13: =G8-G12 -> 28643 | H13: =H8*H55 -> 30842.188 | I13: =I8*I55 -> 33705.172 | J13: =J8*J55 -> 36686.183 | K13: =K8*K55 -> 39922.17 | L13: =L8*L55 -> 43281.972
B15: SG&A | D15: 12144 | E15: 12880 | F15: 13972 | G15: 14582
B16: Add/Less: Extraordinary Items | D16: -5 | E16: 4 | F16: 11 | G16: -24
B17: Normalised SG&A | D17: =SUM(D15:D16) -> 12139 | E17: =SUM(E15:E16) -> 12884 | F17: =SUM(F15:F16) -> 13983 | G17: =SUM(G15:G16) -> 14558 | H17: =H56*H8 -> 15829.221 | I17: =I56*I8 -> 17298.598 | J17: =J56*J8 -> 18828.55 | K17: =K56*K8 -> 20489.365 | L17: =L56*L8 -> 22213.725
B19: Other OpEx | D19: 846 | E19: 1215 | F19: 1951 | G19: 4163
B20: Add/Less: Extraordinary Items | D20: -846 | E20: -1215 | F20: -1951 | G20: -4163
B21: Normalised OpEx | D21: =SUM(D19:D20) -> 0 | E21: =SUM(E19:E20) -> 0 | F21: =SUM(F19:F20) -> 0 | G21: =SUM(G19:G20) -> 0 | H21: =G21 -> 0 | I21: =H21 -> 0 | J21: =I21 -> 0 | K21: =J21 -> 0 | L21: =K21 -> 0
B22: Normalised EBIT | D22: =D13-D17-D21 -> 11109 | E22: =E13-E17-E21 -> 12345 | F22: =F13-F17-F21 -> 13336 | G22: =G13-G17-G21 -> 14085 | H22: =H13-H17-H21 -> 15012.967 | I22: =I13-I17-I21 -> 16406.574 | J22: =J13-J17-J21 -> 17857.633 | K22: =K13-K17-K21 -> 19432.805 | L22: =L13-L17-L21 -> 21068.247
B24: Interest income | D24: 276 | E24: 449 | F24: 907 | G24: 988
B25: Add/Less: Extraordinary Items | D25: 0 | E25: 0 | F25: 0 | G25: 0
B26: Normalised Interest income | D26: =SUM(D24:D25) -> 276 | E26: =SUM(E24:E25) -> 449 | F26: =SUM(F24:F25) -> 907 | G26: =SUM(G24:G25) -> 988 | H26: =H66*AVERAGE('Balance Sheet'!G6:H6) -> 853.0267 | I26: =I66*AVERAGE('Balance Sheet'!H6:I6) -> 916.18101 | J26: =J66*AVERAGE('Balance Sheet'!I6:J6) -> 1056.4943 | K26: =K66*AVERAGE('Balance Sheet'!J6:K6) -> 1132.9978 | L26: =L66*AVERAGE('Balance Sheet'!K6:L6) -> 1114.13
B28: Interest expense | D28: 1597 | E28: 882 | F28: 1527 | G28: 1656
B29: Add/Less: Extraordinary Items | D29: -821 | E29: 24 | F29: 25 | G29: 25
B30: Normalised Interest expense | D30: =SUM(D28:D29) -> 776 | E30: =SUM(E28:E29) -> 906 | F30: =SUM(F28:F29) -> 1552 | G30: =SUM(G28:G29) -> 1681 | H30: =SUM(Debt!D24,Debt!D20) -> 1519.1822 | I30: =SUM(Debt!E24,Debt!E20) -> 1438.8716 | J30: =SUM(Debt!F24,Debt!F20) -> 1308.3587 | K30: =SUM(Debt!G24,Debt!G20) -> 1149.076 | L30: =SUM(Debt!H24,Debt!H20) -> 946.68897
B32: Equity income (loss) — net | D32: 1438 | E32: 1472 | F32: 1691 | G32: 1770
B33: Add/Less: Extraordinary Items | D33: 13 | E33: 34 | F33: 159 | G33: 92
B34: Normalised Equity income (loss) — net | D34: =SUM(D32:D33) -> 1451 | E34: =SUM(E32:E33) -> 1506 | F34: =SUM(F32:F33) -> 1850 | G34: =SUM(G32:G33) -> 1862 | H34: =H59*H8 -> 1965.6055 | I34: =I59*I8 -> 2148.0665 | J34: =J59*J8 -> 2338.0495 | K34: =K59*K8 -> 2544.2824 | L34: =L59*L8 -> 2758.4061
B36: Other income (loss) — net | D36: 2000 | E36: -262 | F36: 570 | G36: 1992
B37: Add/Less: Extraordinary Items | D37: -1633 | E37: 245 | F37: -708 | G37: -1913
B38: Normalised Other income (loss) — net | D38: =SUM(D36:D37) -> 367 | E38: =SUM(E36:E37) -> -17 | F38: =SUM(F36:F37) -> -138 | G38: =SUM(G36:G37) -> 79 | H38: =AVERAGE(E38:G38) -> -25.333333 | I38: =AVERAGE(F38:H38) -> -28.111111 | J38: =AVERAGE(G38:I38) -> 8.5185185 | K38: =AVERAGE(H38:J38) -> -14.975309 | L38: =AVERAGE(I38:K38) -> -11.522634
B39: Normalised PBT | D39: =D22+D26-D30+D34+D38 -> 12427 | E39: =E22+E26-E30+E34+E38 -> 13377 | F39: =F22+F26-F30+F34+F38 -> 14403 | G39: =G22+G26-G30+G34+G38 -> 15333 | H39: =H22+H26-H30+H34+H38 -> 16287.084 | I39: =I22+I26-I30+I34+I38 -> 18003.839 | J39: =J22+J26-J30+J34+J38 -> 19952.336 | K39: =K22+K26-K30+K34+K38 -> 21946.034 | L39: =L22+L26-L30+L34+L38 -> 23982.572
B41: Income Taxes | D41: 2621 | E41: 2115 | F41: 2249 | G41: 2437
B42: Add/Less: Extraordinary Items | D42: -313 | E42: 430 | F42: 488 | G42: 415
B43: Normalised Income Taxes | D43: =SUM(D41:D42) -> 2308 | E43: =SUM(E41:E42) -> 2545 | F43: =SUM(F41:F42) -> 2737 | G43: =SUM(G41:G42) -> 2852 | H43: =H39*H58 -> 3062.0144 | I43: =I39*I58 -> 3384.7688 | J43: =J39*J58 -> 3751.0914 | K43: =K39*K58 -> 4125.9118 | L43: =L39*L58 -> 4508.7861
B44: Consolidated Net Income | D44: =D39-D43 -> 10119 | E44: =E39-E43 -> 10832 | F44: =F39-F43 -> 11666 | G44: =G39-G43 -> 12481 | H44: =H39-H43 -> 13225.07 | I44: =I39-I43 -> 14619.07 | J44: =J39-J43 -> 16201.245 | K44: =K39-K43 -> 17820.122 | L44: =L39-L43 -> 19473.785
B45: Less: Net income (loss) attributable to noncontrolling interests | D45: 33 | E45: 29 | F45: -11 | G45: 18 | H45: =H44*H61 -> 21.284842 | I45: =I44*I61 -> 23.528391 | J45: =J44*J61 -> 26.074792 | K45: =K44*K61 -> 28.680264 | L45: =L44*L61 -> 31.341721
B46: Net Income Attributable to Shareowners of The Coca-Cola Company | D46: =D44-D45 -> 10086 | E46: =E44-E45 -> 10803 | F46: =F44-F45 -> 11677 | G46: =G44-G45 -> 12463 | H46: =H44-H45 -> 13203.785 | I46: =I44-I45 -> 14595.542 | J46: =J44-J45 -> 16175.17 | K46: =K44-K45 -> 17791.442 | L46: =L44-L45 -> 19442.444
B48: Diluted EPS | D48: =D46/D49 -> 2.3239631 | E48: =E46/E49 -> 2.4834483 | F48: =F46/F49 -> 2.6911731 | G48: =G46/G49 -> 2.8849537 | H48: =H46/H49 -> 3.0564317 | I48: =I46/I49 -> 3.3785977 | J48: =J46/J49 -> 3.7442523 | K48: =K46/K49 -> 4.1183894 | L48: =L46/L49 -> 4.5005657
B49: Average Shares Outstanding — Diluted | D49: 4340 | E49: 4350 | F49: 4339 | G49: 4320 | H49: =G49 -> 4320 | I49: =H49 -> 4320 | J49: =I49 -> 4320 | K49: =J49 -> 4320 | L49: =K49 -> 4320
B51: Dividend Per Share | D51: 1.68 | E51: 1.76 | F51: 1.84 | G51: 1.94 | H51: =H52*H48 -> 2.133278 | I51: =I52*I48 -> 2.4443231 | J51: =J52*J48 -> 2.8043768 | K51: =K52*K48 -> 3.1896551 | L51: =L52*L48 -> 3.6004525
B52: Dividend Payout Ratio 2 | D52: =D51/D48 -> 0.72290303 | E52: =E51/E48 -> 0.70869203 | F52: =F51/F48 -> 0.68371671 | G52: =G51/G48 -> 0.67245447 | H52: =G52+($L$52-$G$52)/5 -> 0.69796357 | I52: =H52+($L$52-$G$52)/5 -> 0.72347268 | J52: =I52+($L$52-$G$52)/5 -> 0.74898179 | K52: =J52+($L$52-$G$52)/5 -> 0.77449089 | L52: 0.8
A54: # | B54: Workings
B55: GP margin % | D55: =D13/D8 -> 0.60137617 | E55: =E13/E8 -> 0.58609395 | F55: =F13/F8 -> 0.59669317 | G55: =G13/G8 -> 0.61076401 | H55: =AVERAGE(D55:G55) -> 0.59873182 | I55: =H55 -> 0.59873182 | J55: =I55 -> 0.59873182 | K55: =J55 -> 0.59873182 | L55: =K55 -> 0.59873182
B56: SG&A as % of sales | D56: =D17/D8 -> 0.31401004 | E56: =E17/E8 -> 0.29930772 | F56: =F17/F8 -> 0.30541237 | G56: =G17/G8 -> 0.31042497 | H56: =AVERAGE(D56:G56) -> 0.30728877 | I56: =H56 -> 0.30728877 | J56: =I56 -> 0.30728877 | K56: =J56 -> 0.30728877 | L56: =K56 -> 0.30728877
B57: EBIT margin % | D57: =D22/D8 -> 0.28736613 | E57: =E22/E8 -> 0.28678623 | F57: =F22/F8 -> 0.2912808 | G57: =G22/G8 -> 0.30033904 | H57: =AVERAGE(D57:G57) -> 0.29144305 | I57: =H57 -> 0.29144305 | J57: =I57 -> 0.29144305 | K57: =J57 -> 0.29144305 | L57: =K57 -> 0.29144305
B58: Effective tax rate % | D58: =D43/D39 -> 0.18572463 | E58: =E43/E39 -> 0.19025192 | F58: =F43/F39 -> 0.19002985 | G58: =G43/G39 -> 0.18600404 | H58: =AVERAGE(D58:G58) -> 0.18800261 | I58: =H58 -> 0.18800261 | J58: =I58 -> 0.18800261 | K58: =J58 -> 0.18800261 | L58: =K58 -> 0.18800261
B59: Equity Income as % of sales | D59: =D34/D8 -> 0.037534275 | E59: =E34/E8 -> 0.034985829 | F59: =F34/F8 -> 0.040407129 | G59: =G34/G8 -> 0.039704032 | H59: =AVERAGE(D59:G59) -> 0.038157816 | I59: =H59 -> 0.038157816 | J59: =I59 -> 0.038157816 | K59: =J59 -> 0.038157816 | L59: =K59 -> 0.038157816
B60: Net profit margin | D60: =D44/D8 -> 0.26175695 | E60: =E44/E8 -> 0.25163778 | F60: =F44/F8 -> 0.25480517 | G60: =G44/G8 -> 0.26613643 | H60: =H44/H8 -> 0.25673503 | I60: =I44/I8 -> 0.25969019 | J60: =J44/J8 -> 0.2644102 | K60: =K44/K8 -> 0.26725688 | L60: =L44/L8 -> 0.26938641
B61: Noncontrolling interests as % of Conso. Net income | D61: =D45/D44 -> 0.0032611918 | E61: =E45/E44 -> 0.0026772526 | F61: =F45/F44 -> -0.00094291102 | G61: =G45/G44 -> 0.0014421921 | H61: =AVERAGE(D61:G61) -> 0.0016094314 | I61: =H61 -> 0.0016094314 | J61: =I61 -> 0.0016094314 | K61: =J61 -> 0.0016094314 | L61: =K61 -> 0.0016094314
B62: Normalised EBITDA | D62: =D22+D63 -> 12561 | E62: =E22+E63 -> 13605 | F62: =F22+F63 -> 14464 | G62: =G22+G63 -> 15160 | H62: =H22+H63 -> 16143.77 | I62: =I22+I63 -> 17567.737 | J62: =J22+J63 -> 19060.939 | K62: =K22+K63 -> 20674.21 | L62: =L22+L63 -> 22355.399
B63: Depreciation and amortization | D63: 1452 | E63: 1260 | F63: 1128 | G63: 1075 | H63: =CapEx!H19 -> 1130.8021 | I63: =CapEx!I19 -> 1161.1629 | J63: =CapEx!J19 -> 1203.3066 | K63: =CapEx!K19 -> 1241.4044 | L63: =CapEx!L19 -> 1287.1522
B64: EBITDA margin | D64: =D63/D8 -> 0.037560143 | E64: =E63/E8 -> 0.029271012 | F64: =F63/F8 -> 0.024637428 | G64: =G63/G8 -> 0.022922575 | H64: =H63/H8 -> 0.021951984 | I64: =I63/I8 -> 0.020626661 | J64: =J63/J8 -> 0.019638402 | K64: =K63/K8 -> 0.018617933 | L64: =L63/L8 -> 0.017805543
B65: Dividend | D65: =D51*D49 -> 7291.2 | E65: =E51*E49 -> 7656 | F65: =F51*F49 -> 7983.76 | G65: =G51*G49 -> 8380.8 | H65: =H51*H49 -> 9215.7609 | I65: =I51*I49 -> 10559.476 | J65: =J51*J49 -> 12114.908 | K65: =K51*K49 -> 13779.31 | L65: =L51*L49 -> 15553.955
A66: # | B66: Yield on cash | E66: =E26/AVERAGE('Balance Sheet'!E6,'Balance Sheet'!D6) -> 0.046763527 | F66: =F26/AVERAGE('Balance Sheet'!F6,'Balance Sheet'!E6) -> 0.09605507 | G66: =G26/AVERAGE('Balance Sheet'!G6,'Balance Sheet'!F6) -> 0.097850847 | H66: =AVERAGE($E$66:$G$66) -> 0.080223148 | I66: =H66 -> 0.080223148 | J66: =I66 -> 0.080223148 | K66: =J66 -> 0.080223148 | L66: =K66 -> 0.080223148
A68: # | B68: Notes -
B69: 1. Items in the income statement are converted into from GAAP to Non-GAAP measures to represent a more relevant picture of the company's performance, Extraordinary items under GAAP are taken from Coca-Cola's 8k report for the respective years
B70: 2. Dividend payout ratio is modelled to increase over the years as the assumption is that they will increase their dividend payments due to historical data and the maturity of the company

Sheet Balance Sheet
B2: Particulars | C2: Unit | D2: Historical | H2: Forecast
A3: # | D3: 2021 | E3: =D3+1 -> 2022 | F3: =E3+1 -> 2023 | G3: =F3+1 -> 2024 | H3: =G3+1 -> 2025 | I3: =H3+1 -> 2026 | J3: =I3+1 -> 2027 | K3: =J3+1 -> 2028 | L3: =K3+1 -> 2029
B4: Assets
B5: Current Assets | C5: $
B6: Cash and cash equivalents | D6: 9684 | E6: 9519 | F6: 9366 | G6: 10828 | H6: =CFS!D42 -> 10438.348 | I6: =CFS!E42 -> 12402.466 | J6: =CFS!F42 -> 13936.423 | K6: =CFS!G42 -> 14309.735 | L6: =CFS!H42 -> 13466.039
B7: Short-term investments | D7: 1242 | E7: 1043 | F7: 2997 | G7: 2020 | H7: =G7 -> 2020 | I7: =H7 -> 2020 | J7: =I7 -> 2020 | K7: =J7 -> 2020 | L7: =K7 -> 2020
B8: Total Cash, Cash Equivalents and Short-Term Investments | D8: =SUM(D6:D7) -> 10926 | E8: =SUM(E6:E7) -> 10562 | F8: =SUM(F6:F7) -> 12363 | G8: =SUM(G6:G7) -> 12848 | H8: =SUM(H6:H7) -> 12458.348 | I8: =SUM(I6:I7) -> 14422.466 | J8: =SUM(J6:J7) -> 15956.423 | K8: =SUM(K6:K7) -> 16329.735 | L8: =SUM(L6:L7) -> 15486.039
B9: Marketable securities | D9: 1699 | E9: 1069 | F9: 1300 | G9: 1723 | H9: =G9 -> 1723 | I9: =H9 -> 1723 | J9: =I9 -> 1723 | K9: =J9 -> 1723 | L9: =K9 -> 1723
B10: Trade accounts receivable | D10: 3512 | E10: 3487 | F10: 3410 | G10: 3569 | H10: =H46 -> 3728.9509 | I10: =I46 -> 3866.0355 | J10: =J46 -> 3980.4094 | K10: =K46 -> 4083.8861 | L10: =L46 -> 4159.1169
B11: Inventories | D11: 3414 | E11: 4233 | F11: 4424 | G11: 4728 | H11: =H50 -> 5415.7089 | I11: =I50 -> 5986.0228 | J11: =J50 -> 6589.0173 | K11: =K50 -> 7250.2743 | L11: =L50 -> 7947.2441
B12: Prepaid expenses and other current assets | D12: 2994 | E12: 3240 | F12: 5235 | G12: 3129 | H12: =H54 -> 3480.6509 | I12: =I54 -> 3803.7488 | J12: =J54 -> 4140.1665 | K12: =K54 -> 4505.3592 | L12: =L54 -> 4884.5248
B13: Total Current Assets | D13: =D8+SUM(D9:D12) -> 22545 | E13: =E8+SUM(E9:E12) -> 22591 | F13: =F8+SUM(F9:F12) -> 26732 | G13: =G8+SUM(G9:G12) -> 25997 | H13: =H8+SUM(H9:H12) -> 26806.659 | I13: =I8+SUM(I9:I12) -> 29801.273 | J13: =J8+SUM(J9:J12) -> 32389.016 | K13: =K8+SUM(K9:K12) -> 33892.254 | L13: =L8+SUM(L9:L12) -> 34199.925
B14: Equity method investments | D14: 17598 | E14: 18264 | F14: 19671 | G14: 18087 | H14: =G14 -> 18087 | I14: =H14 -> 18087 | J14: =I14 -> 18087 | K14: =J14 -> 18087 | L14: =K14 -> 18087
B15: Deferred income tax assets | D15: 2129 | E15: 1746 | F15: 1561 | G15: 1319 | H15: =G15 -> 1319 | I15: =H15 -> 1319 | J15: =I15 -> 1319 | K15: =J15 -> 1319 | L15: =K15 -> 1319
B16: Property, plant and equipment — net | D16: 9920 | E16: 9841 | F16: 9236 | G16: 10303 | H16: =CapEx!H10 -> 10058.688 | I16: =CapEx!I10 -> 9754.0669 | J16: =CapEx!J10 -> 9403.1293 | K16: =CapEx!K10 -> 9082.1235 | L16: =CapEx!L10 -> 8708.6428
B17: Trademarks with indefinite lives | D17: 14465 | E17: 14214 | F17: 14349 | G17: 13301 | H17: =G17 -> 13301 | I17: =H17 -> 13301 | J17: =I17 -> 13301 | K17: =J17 -> 13301 | L17: =K17 -> 13301
B18: Goodwill | D18: 19363 | E18: 18782 | F18: 18358 | G18: 18139 | H18: =G18 -> 18139 | I18: =H18 -> 18139 | J18: =I18 -> 18139 | K18: =J18 -> 18139 | L18: =K18 -> 18139
B19: Other noncurrent assets | D19: =D40 -> 8334 | E19: =E40 -> 7325 | F19: 7796 | G19: 13403 | H19: =CapEx!H15 -> 13349 | I19: =CapEx!I15 -> 13307 | J19: =CapEx!J15 -> 13265 | K19: =CapEx!K15 -> 13231 | L19: =CapEx!L15 -> 13197
B20: Total Assets | D20: =SUM(D13:D19) -> 94354 | E20: =SUM(E13:E19) -> 92763 | F20: =SUM(F13:F19) -> 97703 | G20: =SUM(G13:G19) -> 100549 | H20: =SUM(H13:H19) -> 101060.35 | I20: =SUM(I13:I19) -> 103708.34 | J20: =SUM(J13:J19) -> 105903.15 | K20: =SUM(K13:K19) -> 107051.38 | L20: =SUM(L13:L19) -> 106951.57
B22: Liabilities and Equity
B23: Current Liabilities
B24: Accounts payable and accrued expenses | D24: 14619 | E24: 15749 | F24: 15485 | G24: 21715 | H24: =H58 -> 19951.095 | I24: =I58 -> 21803.093 | J24: =J58 -> 23731.439 | K24: =K58 -> 25824.725 | L24: =L58 -> 27998.103
B25: Loans and notes payable | D25: 3307 | E25: 2373 | F25: 4557 | G25: 1499 | H25: =Debt!D17 -> 2893.8059 | I25: =Debt!E17 -> 2422.5484 | J25: =Debt!F17 -> 2301.812 | K25: =Debt!G17 -> 1944.7573 | L25: =Debt!H17 -> 1494.9771
B26: Current maturities of long-term debt | D26: 1338 | E26: 399 | F26: 1960 | G26: 648 | H26: =-Debt!E8 -> 1803 | I26: =-Debt!F8 -> 5064 | J26: =-Debt!G8 -> 2786 | K26: =-Debt!H8 -> 2684 | L26: =K26 -> 2684
B27: Accrued income taxes | D27: 686 | E27: 1203 | F27: 1569 | G27: 1387 | H27: =H61 -> 1400.4883 | I27: =I61 -> 1548.1081 | J27: =J61 -> 1715.6548 | K27: =K61 -> 1887.0882 | L27: =L61 -> 2062.2053
B28: Total Current Liabilities | D28: =SUM(D24:D27) -> 19950 | E28: =SUM(E24:E27) -> 19724 | F28: =SUM(F24:F27) -> 23571 | G28: =SUM(G24:G27) -> 25249 | H28: =SUM(H24:H27) -> 26048.39 | I28: =SUM(I24:I27) -> 30837.75 | J28: =SUM(J24:J27) -> 30534.906 | K28: =SUM(K24:K27) -> 32340.57 | L28: =SUM(L24:L27) -> 34239.285
B29: Long-term debt | D29: 38116 | E29: 36377 | F29: 35547 | G29: 42375 | H29: =Debt!D11 -> 38077.648 | I29: =Debt!E11 -> 31876.687 | J29: =Debt!F11 -> 30287.999 | K29: =Debt!G11 -> 25589.755 | L29: =Debt!H11 -> 19671.399
B30: Other noncurrent liabilities | D30: 8607 | E30: 7922 | F30: 8466 | G30: 4084 | H30: =G30 -> 4084 | I30: =H30 -> 4084 | J30: =I30 -> 4084 | K30: =J30 -> 4084 | L30: =K30 -> 4084
B31: Deferred income tax liabilities | D31: 2821 | E31: 2914 | F31: 2639 | G31: 2469 | H31: =G31 -> 2469 | I31: =H31 -> 2469 | J31: =I31 -> 2469 | K31: =J31 -> 2469 | L31: =K31 -> 2469
B32: Equity Attributable to Shareowners of The Coca-Cola Company | D32: 22999 | E32: 24105 | F32: 25941 | G32: 24856 | H32: =G32+'P&L'!H46-'P&L'!H65 -> 28844.024 | I32: =H32+'P&L'!I46-'P&L'!I65 -> 32880.09 | J32: =I32+'P&L'!J46-'P&L'!J65 -> 36940.352 | K32: =J32+'P&L'!K46-'P&L'!K65 -> 40952.485 | L32: =K32+'P&L'!L46-'P&L'!L65 -> 44840.973
B33: Equity attributable to noncontrolling interests | D33: 1861 | E33: 1721 | F33: 1539 | G33: 1516 | H33: =G33+'P&L'!H45 -> 1537.2848 | I33: =H33+'P&L'!I45 -> 1560.8132 | J33: =I33+'P&L'!J45 -> 1586.888 | K33: =J33+'P&L'!K45 -> 1615.5683 | L33: =K33+'P&L'!L45 -> 1646.91
B34: Total Equity | D34: =SUM(D32:D33) -> 24860 | E34: =SUM(E32:E33) -> 25826 | F34: =SUM(F32:F33) -> 27480 | G34: =SUM(G32:G33) -> 26372 | H34: =SUM(H32:H33) -> 30381.309 | I34: =SUM(I32:I33) -> 34440.903 | J34: =SUM(J32:J33) -> 38527.24 | K34: =SUM(K32:K33) -> 42568.053 | L34: =SUM(L32:L33) -> 46487.883
B35: Total Liabilities and Equity | D35: =SUM(D34,D28:D31) -> 94354 | E35: =SUM(E34,E28:E31) -> 92763 | F35: =SUM(F34,F28:F31) -> 97703 | G35: =SUM(G34,G28:G31) -> 100549 | H35: =SUM(H34,H28:H31) -> 101060.35 | I35: =SUM(I34,I28:I31) -> 103708.34 | J35: =SUM(J34,J28:J31) -> 105903.15 | K35: =SUM(K34,K28:K31) -> 107051.38 | L35: =SUM(L34,L28:L31) -> 106951.57
B37: Difference | D37: =D20-D35 -> 0 | E37: =E20-E35 -> 0 | F37: =F20-F35 -> 0 | G37: =G20-G35 -> 0 | H37: =H20-H35 -> 0 | I37: =I20-I35 -> 0 | J37: =J20-J35 -> 0 | K37: =K20-K35 -> 0 | L37: =L20-L35 -> 0
B39: Workings -
B40: Other Non-Current Assets | D40: =SUM(D41:D43) -> 8334 | E40: =SUM(E41:E43) -> 7325
B41: Other investments | D41: 818 | E41: 501 | F41: 118 | G41: =F41 -> 118 | H41: =G41 -> 118 | I41: =H41 -> 118 | J41: =I41 -> 118 | K41: =J41 -> 118 | L41: =K41 -> 118
B42: Other noncurrent assets | D42: 6731 | E42: 6189
B43: Other intangible assets | D43: 785 | E43: 635
B45: Current assets
B46: Trade accounts receivable | D46: =D10 -> 3512 | E46: =E10 -> 3487 | F46: =F10 -> 3410 | G46: =G10 -> 3569 | H46: ='P&L'!H8/H47 -> 3728.9509 | I46: ='P&L'!I8/I47 -> 3866.0355 | J46: ='P&L'!J8/J47 -> 3980.4094 | K46: ='P&L'!K8/K47 -> 4083.8861 | L46: ='P&L'!L8/L47 -> 4159.1169
B47: Receivable turnover ratio | D47: ='P&L'!D8/'Balance Sheet'!D46 -> 11.007403 | E47: ='P&L'!E8/'Balance Sheet'!E46 -> 12.344709 | F47: ='P&L'!F8/'Balance Sheet'!F46 -> 13.426393 | G47: ='P&L'!G8/'Balance Sheet'!G46 -> 13.140095 | H47: =365/H48 -> 13.814214 | I47: =365/I48 -> 14.56124 | J47: =365/J48 -> 15.393679 | K47: =365/K48 -> 16.327067 | L47: =365/L48 -> 17.380952
B48: Receivable days | D48: =365/D47 -> 33.159501 | E48: =365/E47 -> 29.567323 | F48: =365/F47 -> 27.185261 | G48: =365/G47 -> 27.777576 | H48: =G48-(($G$48-$L$48)/5) -> 26.422061 | I48: =H48-(($G$48-$L$48)/5) -> 25.066546 | J48: =I48-(($G$48-$L$48)/5) -> 23.711031 | K48: =J48-(($G$48-$L$48)/5) -> 22.355515 | L48: 21
B50: Inventories | D50: =D11 -> 3414 | E50: =E11 -> 4233 | F50: =F11 -> 4424 | G50: =G11 -> 4728 | H50: ='P&L'!H12/H51 -> 5415.7089 | I50: ='P&L'!I12/I51 -> 5986.0228 | J50: ='P&L'!J12/J51 -> 6589.0173 | K50: ='P&L'!K12/K51 -> 7250.2743 | L50: ='P&L'!L12/L51 -> 7947.2441
B51: Inventory turnover ratio | D51: ='P&L'!D12/'Balance Sheet'!D50 -> 4.5137668 | E51: ='P&L'!E12/'Balance Sheet'!E50 -> 4.2090716 | F51: ='P&L'!F12/'Balance Sheet'!F50 -> 4.1738246 | G51: ='P&L'!G12/'Balance Sheet'!G50 -> 3.8608291 | H51: =365/H52 -> 3.8167371 | I51: =365/I52 -> 3.7736408 | J51: =365/J52 -> 3.7315069 | K51: =365/K52 -> 3.6903034 | L51: =365/L52 -> 3.65
B52: Inventory days | D52: =365/D51 -> 80.863725 | E52: =365/E51 -> 86.717461 | F52: =365/F51 -> 87.44977 | G52: =365/G51 -> 94.539279 | H52: =G52-(($G$52-$L$52)/5) -> 95.631423 | I52: =H52-(($G$52-$L$52)/5) -> 96.723567 | J52: =I52-(($G$52-$L$52)/5) -> 97.815712 | K52: =J52-(($G$52-$L$52)/5) -> 98.907856 | L52: 100
B54: Prepaid expenses and other current assets | D54: =D12 -> 2994 | E54: =E12 -> 3240 | F54: =F12 -> 5235 | G54: =G12 -> 3129 | H54: =SUM('P&L'!H12,'P&L'!H17)*H55 -> 3480.6509 | I54: =SUM('P&L'!I12,'P&L'!I17)*I55 -> 3803.7488 | J54: =SUM('P&L'!J12,'P&L'!J17)*J55 -> 4140.1665 | K54: =SUM('P&L'!K12,'P&L'!K17)*K55 -> 4505.3592 | L54: =SUM('P&L'!L12,'P&L'!L17)*L55 -> 4884.5248
B55: Prepaid expenses and other current assets as % of (COGS & SG&A) | D55: =D54/SUM('P&L'!D12,'P&L'!D17) -> 0.10867908 | E55: =E54/SUM('P&L'!E12,'P&L'!E17) -> 0.10553402 | F55: =F54/SUM('P&L'!F12,'P&L'!F17) -> 0.16133506 | G55: =G54/SUM('P&L'!G12,'P&L'!G17) -> 0.095361453 | H55: =G55 -> 0.095361453 | I55: =H55 -> 0.095361453 | J55: =I55 -> 0.095361453 | K55: =J55 -> 0.095361453 | L55: =K55 -> 0.095361453
B57: Current Liabilities
B58: Accounts payable and accrued expenses | D58: =D24 -> 14619 | E58: =E24 -> 15749 | F58: =F24 -> 15485 | G58: =G24 -> 21715 | H58: =H59*'P&L'!H12 -> 19951.095 | I58: =I59*'P&L'!I12 -> 21803.093 | J58: =J59*'P&L'!J12 -> 23731.439 | K58: =K59*'P&L'!K12 -> 25824.725 | L58: =L59*'P&L'!L12 -> 27998.103
B59: Accounts payable and accrued expenses as % of COGS | D59: =D58/'P&L'!D12 -> 0.9486697 | E59: =E58/'P&L'!E12 -> 0.88393108 | F59: =F58/'P&L'!F12 -> 0.83861359 | G59: =G58/'P&L'!G12 -> 1.1896023 | H59: =AVERAGE($D$59:$G$59) -> 0.96520416 | I59: =H59 -> 0.96520416 | J59: =I59 -> 0.96520416 | K59: =J59 -> 0.96520416 | L59: =K59 -> 0.96520416
B61: Accrued income taxes | D61: =D27 -> 686 | E61: =E27 -> 1203 | F61: =F27 -> 1569 | G61: =G27 -> 1387 | H61: =H62*'P&L'!H43 -> 1400.4883 | I61: =I62*'P&L'!I43 -> 1548.1081 | J61: =J62*'P&L'!J43 -> 1715.6548 | K61: =K62*'P&L'!K43 -> 1887.0882 | L61: =L62*'P&L'!L43 -> 2062.2053
B62: Accrued income taxes as % of Income tax | D62: =D61/'P&L'!D43 -> 0.29722704 | E62: =E61/'P&L'!E43 -> 0.47269155 | F62: =F61/'P&L'!F43 -> 0.57325539 | G62: =G61/'P&L'!G43 -> 0.48632539 | H62: =AVERAGE($D$62:$G$62) -> 0.45737484 | I62: =H62 -> 0.45737484 | J62: =I62 -> 0.45737484 | K62: =J62 -> 0.45737484 | L62: =K62 -> 0.45737484
B64: Total Long Term Debt / EBITDA | D64: =SUM(D29,D26)/'P&L'!D62 -> 3.140992 | E64: =SUM(E29,E26)/'P&L'!E62 -> 2.7031239 | F64: =SUM(F29,F26)/'P&L'!F62 -> 2.5931278 | G64: =SUM(G29,G26)/'P&L'!G62 -> 2.8379288 | H64: =G64-($G$64-$L$64)/5 -> 2.470343 | I64: =H64-($G$64-$L$64)/5 -> 2.1027573 | J64: =I64-($G$64-$L$64)/5 -> 1.7351715 | K64: =J64-($G$64-$L$64)/5 -> 1.3675858 | L64: 1
A65: # | B65: Loans and Notes Payables as a % of Long Term Debt | D65: =D25/D29 -> 0.086761465 | E65: =E25/E29 -> 0.065233527 | F65: =F25/F29 -> 0.12819647 | G65: =G25/G29 -> 0.035374631 | H65: =MEDIAN($D$65:$G$65) -> 0.075997496 | I65: =H65 -> 0.075997496 | J65: =I65 -> 0.075997496 | K65: =J65 -> 0.075997496 | L65: =K65 -> 0.075997496
A67: # | B67: Notes -
B68: 1. BS line items such as; Short-term investments, Marketable securities, Equity method investments, Deferred income tax assets, Trademarks with indefinite lives, Goodwill, Other noncurrent liabilities, Deferred income tax liabilities, Other investments, Prepaid expenses are straight lined for forecasting simplicity purpose.

Sheet CFS
B2: Particulars | C2: Unit | D2: Forecast
A3: # | D3: 2025 | E3: =D3+1 -> 2026 | F3: =E3+1 -> 2027 | G3: =F3+1 -> 2028 | H3: =G3+1 -> 2029
B5: Cash Flow from Operations - | C5: $
B6: Consolidated Net Income | D6: ='P&L'!H44 -> 13225.07 | E6: ='P&L'!I44 -> 14619.07 | F6: ='P&L'!J44 -> 16201.245 | G6: ='P&L'!K44 -> 17820.122 | H6: ='P&L'!L44 -> 19473.785
B8: Add/Less: Non Cash/Non Operating items -
B9: Depreciation and Amortization | D9: =CapEx!H19 -> 1130.8021 | E9: =CapEx!I19 -> 1161.1629 | F9: =CapEx!J19 -> 1203.3066 | G9: =CapEx!K19 -> 1241.4044 | H9: =CapEx!L19 -> 1287.1522
B10: Interest Income | D10: =-'P&L'!H26 -> -853.0267 | E10: =-'P&L'!I26 -> -916.18101 | F10: =-'P&L'!J26 -> -1056.4943 | G10: =-'P&L'!K26 -> -1132.9978 | H10: =-'P&L'!L26 -> -1114.13
B11: Interest Expense | D11: ='P&L'!H30 -> 1519.1822 | E11: ='P&L'!I30 -> 1438.8716 | F11: ='P&L'!J30 -> 1308.3587 | G11: ='P&L'!K30 -> 1149.076 | H11: ='P&L'!L30 -> 946.68897
B12: Equity Income | D12: =-'P&L'!H34 -> -1965.6055 | E12: =-'P&L'!I34 -> -2148.0665 | F12: =-'P&L'!J34 -> -2338.0495 | G12: =-'P&L'!K34 -> -2544.2824 | H12: =-'P&L'!L34 -> -2758.4061
B13: Other Income | D13: =-'P&L'!H38 -> 25.333333 | E13: =-'P&L'!I38 -> 28.111111 | F13: =-'P&L'!J38 -> -8.5185185 | G13: =-'P&L'!K38 -> 14.975309 | H13: =-'P&L'!L38 -> 11.522634
B14: Cash Flow from Operations before Working Capital Changes | D14: =SUM(D6:D13) -> 13081.755 | E14: =SUM(E6:E13) -> 14182.968 | F14: =SUM(F6:F13) -> 15309.848 | G14: =SUM(G6:G13) -> 16548.298 | H14: =SUM(H6:H13) -> 17846.613
B16: Changes in Working Capital -
B17: Trade accounts receivable | D17: =-('Balance Sheet'!H10-'Balance Sheet'!G10) -> -159.95093 | E17: =-('Balance Sheet'!I10-'Balance Sheet'!H10) -> -137.08457 | F17: =-('Balance Sheet'!J10-'Balance Sheet'!I10) -> -114.37392 | G17: =-('Balance Sheet'!K10-'Balance Sheet'!J10) -> -103.47663 | H17: =-('Balance Sheet'!L10-'Balance Sheet'!K10) -> -75.230865
B18: Inventories | D18: =-('Balance Sheet'!H11-'Balance Sheet'!G11) -> -687.70889 | E18: =-('Balance Sheet'!I11-'Balance Sheet'!H11) -> -570.31393 | F18: =-('Balance Sheet'!J11-'Balance Sheet'!I11) -> -602.99453 | G18: =-('Balance Sheet'!K11-'Balance Sheet'!J11) -> -661.25692 | H18: =-('Balance Sheet'!L11-'Balance Sheet'!K11) -> -696.96981
B19: Prepaid expenses and other current assets | D19: =-('Balance Sheet'!H12-'Balance Sheet'!G12) -> -351.65087 | E19: =-('Balance Sheet'!I12-'Balance Sheet'!H12) -> -323.09796 | F19: =-('Balance Sheet'!J12-'Balance Sheet'!I12) -> -336.41762 | G19: =-('Balance Sheet'!K12-'Balance Sheet'!J12) -> -365.19271 | H19: =-('Balance Sheet'!L12-'Balance Sheet'!K12) -> -379.16566
B20: Accounts payable and accrued expenses | D20: ='Balance Sheet'!H24-'Balance Sheet'!G24 -> -1763.9047 | E20: ='Balance Sheet'!I24-'Balance Sheet'!H24 -> 1851.998 | F20: ='Balance Sheet'!J24-'Balance Sheet'!I24 -> 1928.3462 | G20: ='Balance Sheet'!K24-'Balance Sheet'!J24 -> 2093.2851 | H20: ='Balance Sheet'!L24-'Balance Sheet'!K24 -> 2173.3781
B21: Accrued Income Taxes | D21: =('Balance Sheet'!H27-'Balance Sheet'!G27) -> 13.488344 | E21: =('Balance Sheet'!I27-'Balance Sheet'!H27) -> 147.61977 | F21: =('Balance Sheet'!J27-'Balance Sheet'!I27) -> 167.5467 | G21: =('Balance Sheet'!K27-'Balance Sheet'!J27) -> 171.43344 | H21: =('Balance Sheet'!L27-'Balance Sheet'!K27) -> 175.1171
B22: Cash Generated from Operations | D22: =SUM(D14:D21) -> 10132.028 | E22: =SUM(E14:E21) -> 15152.09 | F22: =SUM(F14:F21) -> 16351.955 | G22: =SUM(G14:G21) -> 17683.09 | H22: =SUM(H14:H21) -> 19043.742
B24: Cash from Investing -
B25: Net Purchase/Sale of PPE | D25: =-CapEx!H7 -> -832.49001 | E25: =-CapEx!I7 -> -814.54187 | F25: =-CapEx!J7 -> -810.3691 | G25: =-CapEx!K7 -> -886.39859 | H25: =-CapEx!L7 -> -879.67146
B26: Purchase of Intangibles | D26: 0 | E26: 0 | F26: 0 | G26: 0 | H26: 0
B27: Interest Income | D27: =-D10 -> 853.0267 | E27: =-E10 -> 916.18101 | F27: =-F10 -> 1056.4943 | G27: =-G10 -> 1132.9978 | H27: =-H10 -> 1114.13
B28: Equity Income | D28: ='P&L'!H34 -> 1965.6055 | E28: ='P&L'!I34 -> 2148.0665 | F28: ='P&L'!J34 -> 2338.0495 | G28: ='P&L'!K34 -> 2544.2824 | H28: ='P&L'!L34 -> 2758.4061
B29: Other Income | D29: ='P&L'!H38 -> -25.333333 | E29: ='P&L'!I38 -> -28.111111 | F29: ='P&L'!J38 -> 8.5185185 | G29: ='P&L'!K38 -> -14.975309 | H29: ='P&L'!L38 -> -11.522634
B30: Cash Generated from Investing | D30: =SUM(D25:D29) -> 1960.8088 | E30: =SUM(E25:E29) -> 2221.5945 | F30: =SUM(F25:F29) -> 2592.6932 | G30: =SUM(G25:G29) -> 2775.9063 | H30: =SUM(H25:H29) -> 2981.3421
B32: Cash Flow from Financing
B33: Debt Raised | D33: =SUM(Debt!D7,Debt!D15) -> -1099.5457 | E33: =SUM(Debt!E7,Debt!E15) -> -1136.9612 | F33: =SUM(Debt!F7,Debt!F15) -> 1197.3115 | G33: =SUM(Debt!G7,Debt!G15) -> -2014.244 | H33: =SUM(Debt!H7,Debt!H15) -> -3234.3553
B34: Debt Repaid | D34: =Debt!D8+Debt!D16 -> -648 | E34: =Debt!E8+Debt!E16 -> -2274.2575 | F34: =Debt!F8+Debt!F16 -> -5184.7363 | G34: =Debt!G8+Debt!G16 -> -3143.0548 | H34: =Debt!H8+Debt!H16 -> -3133.7802
B35: Interest Expense | D35: =-D11 -> -1519.1822 | E35: =-E11 -> -1438.8716 | F35: =-F11 -> -1308.3587 | G35: =-G11 -> -1149.076 | H35: =-H11 -> -946.68897
B36: Dividend | D36: =-'P&L'!H65 -> -9215.7609 | E36: =-'P&L'!I65 -> -10559.476 | F36: =-'P&L'!J65 -> -12114.908 | G36: =-'P&L'!K65 -> -13779.31 | H36: =-'P&L'!L65 -> -15553.955
B37: Cash Generated from Financing | D37: =SUM(D33:D36) -> -12482.489 | E37: =SUM(E33:E36) -> -15409.566 | F37: =SUM(F33:F36) -> -17410.691 | G37: =SUM(G33:G36) -> -20085.685 | H37: =SUM(H33:H36) -> -22868.779
B39: Total Cash Generated during the Year | D39: =SUM(D37,D30,D22) -> -389.65183 | E39: =SUM(E37,E30,E22) -> 1964.118 | F39: =SUM(F37,F30,F22) -> 1533.9566 | G39: =SUM(G37,G30,G22) -> 373.31176 | H39: =SUM(H37,H30,H22) -> -843.69541
B41: Add: Opening Balance of Cash and Cash Equivalents | D41: ='Balance Sheet'!G6 -> 10828 | E41: =D42 -> 10438.348 | F41: =E42 -> 12402.466 | G41: =F42 -> 13936.423 | H41: =G42 -> 14309.735
A42: # | B42: Closing Balance | D42: =SUM(D39:D41) -> 10438.348 | E42: =SUM(E39:E41) -> 12402.466 | F42: =SUM(F39:F41) -> 13936.423 | G42: =SUM(G39:G41) -> 14309.735 | H42: =SUM(H39:H41) -> 13466.039

Sheet Supporting Schedules>

Sheet CapEx
A2: # | B2: Particulars | C2: Unit | D2: Historical | H2: Forecast
D3: 2021 | E3: =D3+1 -> 2022 | F3: =E3+1 -> 2023 | G3: =F3+1 -> 2024 | H3: =G3+1 -> 2025 | I3: =H3+1 -> 2026 | J3: =I3+1 -> 2027 | K3: =J3+1 -> 2028 | L3: =K3+1 -> 2029
B5: Propert, Plant and Equipment - | C5: $
B6: Opening Gross Block | D6: 19700 | E6: =D8 -> 18862 | F6: =E8 -> 19075 | G6: =F8 -> 18469 | H6: =G8 -> 19873 | I6: =H8 -> 20705.49 | J6: =I8 -> 21520.032 | K6: =J8 -> 22330.401 | L6: =K8 -> 23216.8
B7: Add: Net Purchases/Sale | D7: =D8-D6 -> -838 | E7: =E8-E6 -> 213 | F7: =F8-F6 -> -606 | G7: =G8-G6 -> 1404 | H7: =H8-H6 -> 832.49001 | I7: =I8-I6 -> 814.54187 | J7: =J8-J6 -> 810.3691 | K7: =K8-K6 -> 886.39859 | L7: =L8-L6 -> 879.67146
B8: Closing Gross Block | D8: 18862 | E8: 19075 | F8: 18469 | G8: 19873 | H8: ='P&L'!H8/CapEx!H21 -> 20705.49 | I8: ='P&L'!I8/CapEx!I21 -> 21520.032 | J8: ='P&L'!J8/CapEx!J21 -> 22330.401 | K8: ='P&L'!K8/CapEx!K21 -> 23216.8 | L8: ='P&L'!L8/CapEx!L21 -> 24096.471
B9: Less: Accumulated Depreciation | D9: 8942 | E9: 9234 | F9: 9233 | G9: 9570 | H9: =G9+H18 -> 10646.802 | I9: =H9+I18 -> 11765.965 | J9: =I9+J18 -> 12927.272 | K9: =J9+K18 -> 14134.676 | L9: =K9+L18 -> 15387.828
B10: Net Block | D10: =D8-D9 -> 9920 | E10: =E8-E9 -> 9841 | F10: =F8-F9 -> 9236 | G10: =G8-G9 -> 10303 | H10: =H8-H9 -> 10058.688 | I10: =I8-I9 -> 9754.0669 | J10: =J8-J9 -> 9403.1293 | K10: =K8-K9 -> 9082.1235 | L10: =L8-L9 -> 8708.6428
B12: Other Non-Current Assets -
B13: Opening Balance | H13: ='Balance Sheet'!G19 -> 13403 | I13: =H15 -> 13349 | J13: =I15 -> 13307 | K13: =J15 -> 13265 | L13: =K15 -> 13231
B14: Less: Amortization | H14: =-H22 -> -54 | I14: =-I22 -> -42 | J14: =-J22 -> -42 | K14: =-K22 -> -34 | L14: =-L22 -> -34
B15: Closing Balance | H15: =SUM(H13:H14) -> 13349 | I15: =SUM(I13:I14) -> 13307 | J15: =SUM(J13:J14) -> 13265 | K15: =SUM(K13:K14) -> 13231 | L15: =SUM(L13:L14) -> 13197
B18: Depreciation | D18: 1262 | E18: 1125 | F18: 1018 | G18: 997 | H18: =H8*H20 -> 1076.8021 | I18: =I8*I20 -> 1119.1629 | J18: =J8*J20 -> 1161.3066 | K18: =K8*K20 -> 1207.4044 | L18: =L8*L20 -> 1253.1522
B19: Depreciation & Amortization | D19: 1452 | E19: 1260 | F19: 1128 | G19: 1075 | H19: =H18+H22 -> 1130.8021 | I19: =I18+I22 -> 1161.1629 | J19: =J18+J22 -> 1203.3066 | K19: =K18+K22 -> 1241.4044 | L19: =L18+L22 -> 1287.1522
B20: Rate of Depreciation | D20: =D18/((D6+D8)/2) -> 0.065453037 | E20: =E18/((E6+E8)/2) -> 0.059308854 | F20: =F18/((F6+F8)/2) -> 0.054229704 | G20: =G18/((G6+G8)/2) -> 0.052005634 | H20: =G20 -> 0.052005634 | I20: =H20 -> 0.052005634 | J20: =I20 -> 0.052005634 | K20: =J20 -> 0.052005634 | L20: =K20 -> 0.052005634
B21: Fixed Asset Turnover Ratio | D21: ='P&L'!D8/CapEx!D8 -> 2.0495175 | E21: ='P&L'!E8/CapEx!E8 -> 2.256671 | F21: ='P&L'!F8/CapEx!F8 -> 2.4789648 | G21: ='P&L'!G8/CapEx!G8 -> 2.359835 | H21: =G21+(($L$21-$G$21)/5) -> 2.487868 | I21: =H21+(($L$21-$G$21)/5) -> 2.615901 | J21: =I21+(($L$21-$G$21)/5) -> 2.743934 | K21: =J21+(($L$21-$G$21)/5) -> 2.871967 | L21: 3
A22: # | B22: Amortization (Forecasted in FS 2023) 1 | H22: 54 | I22: 42 | J22: 42 | K22: 34 | L22: =K22 -> 34 | M22: 2
B24: Notes -
B25: 1. Amortization expense forecast figures not available in the 10K report for FY 24, hence FY 23 figs are taken
B26: 2. Amortization expense for the year 2029 not given in FY23 10K report and hence straight lined forecasted expense from FY2028

Sheet Debt
A2: # | B2: Particulars | C2: Unit | D2: Forecast
D3: 2025 | E3: =D3+1 -> 2026 | F3: =E3+1 -> 2027 | G3: =F3+1 -> 2028 | H3: =G3+1 -> 2029
B5: Long Term Debt - | C5: $
B6: Opening Balance | D6: 43023 | E6: =D9 -> 39880.648 | F6: =E9 -> 36940.687 | G6: =F9 -> 33073.999 | H6: =G9 -> 28273.755
B7: Add: Loan taken | D7: =D9-D6-D8 -> -2494.3517 | E7: =E9-E6-E8 -> -1136.9612 | F7: =F9-F6-F8 -> 1197.3115 | G7: =G9-G6-G8 -> -2014.244 | H7: =H9-H6-H8 -> -3234.3553
B8: Less: Loan repaid | D8: -648 | E8: -1803 | F8: -5064 | G8: -2786 | H8: -2684
B9: Total Debt | D9: =D25*'P&L'!H62 -> 39880.648 | E9: =E25*'P&L'!I62 -> 36940.687 | F9: =F25*'P&L'!J62 -> 33073.999 | G9: =G25*'P&L'!K62 -> 28273.755 | H9: =H25*'P&L'!L62 -> 22355.399
B10: Less: Current Maturities | D10: =E8 -> -1803 | E10: =F8 -> -5064 | F10: =G8 -> -2786 | G10: =H8 -> -2684 | H10: =G10 -> -2684
B11: Closing Balance | D11: =SUM(D9:D10) -> 38077.648 | E11: =SUM(E9:E10) -> 31876.687 | F11: =SUM(F9:F10) -> 30287.999 | G11: =SUM(G9:G10) -> 25589.755 | H11: =SUM(H9:H10) -> 19671.399
B13: Loans and Notes Payable -
B14: Opening Balance | D14: ='Balance Sheet'!G25 -> 1499 | E14: =D17 -> 2893.8059 | F14: =E17 -> 2422.5484 | G14: =F17 -> 2301.812 | H14: =G17 -> 1944.7573
B15: Add: Loan taken | D15: =IF(D17>D14,D17-D14,0) -> 1394.8059 | E15: =IF(E17>E14,E17-E14,0) -> 0 | F15: =IF(F17>F14,F17-F14,0) -> 0 | G15: =IF(G17>G14,G17-G14,0) -> 0 | H15: =IF(H17>H14,H17-H14,0) -> 0
B16: Less: Loan repaid | D16: =IF(D14>D17,-(D14-D17),0) -> 0 | E16: =IF(E14>E17,-(E14-E17),0) -> -471.25753 | F16: =IF(F14>F17,-(F14-F17),0) -> -120.73635 | G16: =IF(G14>G17,-(G14-G17),0) -> -357.05478 | H16: =IF(H14>H17,-(H14-H17),0) -> -449.78018
B17: Closing Balance | D17: =D21*D11 -> 2893.8059 | E17: =E21*E11 -> 2422.5484 | F17: =F21*F11 -> 2301.812 | G17: =G21*G11 -> 1944.7573 | H17: =H21*H11 -> 1494.9771
B19: Average Interest Rate | D19: 0.05 | E19: =D19 -> 0.05 | F19: =E19 -> 0.05 | G19: =F19 -> 0.05 | H19: =G19 -> 0.05
B20: Interest Expenses | D20: =D19*AVERAGE(D14,D17) -> 109.82015 | E20: =E19*AVERAGE(E14,E17) -> 132.90886 | F20: =F19*AVERAGE(F14,F17) -> 118.10901 | G20: =G19*AVERAGE(G14,G17) -> 106.16423 | H20: =H19*AVERAGE(H14,H17) -> 85.993359
B21: Loans and Notes Payables as a % of Long Term Debt | D21: ='Balance Sheet'!H65 -> 0.075997496 | E21: ='Balance Sheet'!I65 -> 0.075997496 | F21: ='Balance Sheet'!J65 -> 0.075997496 | G21: ='Balance Sheet'!K65 -> 0.075997496 | H21: ='Balance Sheet'!L65 -> 0.075997496
B23: Average Interest Rate | D23: 0.034 | E23: =D23 -> 0.034 | F23: =E23 -> 0.034 | G23: =F23 -> 0.034 | H23: =G23 -> 0.034
B24: Interest Expenses | D24: =D23*AVERAGE(D6,D9) -> 1409.362 | E24: =E23*AVERAGE(E6,E9) -> 1305.9627 | F24: =F23*AVERAGE(F6,F9) -> 1190.2497 | G24: =G23*AVERAGE(G6,G9) -> 1042.9118 | H24: =H23*AVERAGE(H6,H9) -> 860.69562
A25: # | B25: Total Long Term Debt / EBITDA | D25: ='Balance Sheet'!H64 -> 2.470343 | E25: ='Balance Sheet'!I64 -> 2.1027573 | F25: ='Balance Sheet'!J64 -> 1.7351715 | G25: ='Balance Sheet'!K64 -> 1.3675858 | H25: ='Balance Sheet'!L64 -> 1

Sheet Cost of Capital>

Sheet Cost of Debt
A2: # | B2: Calculation of Cost of Debt
B5: As per Long Term Bond in Coca-Cola 10K 2024
B6: Name of Bond | C6: Coca-Cola Company 7.375% 29-JUL-2093
B7: Symbol | C7: KO.GC
B8: Cost of Debt | C8: =C21*(1-C9) -> 0.043431854
B9: Marginal Tax Rate 1 | C9: =Valuation!D5 -> 0.27
B10: Yield of Coca-Cola Bond -
B11: Frequency | C11: Semi-Annual
B12: FV | C12: 1000
B13: CMP | C13: 1.23597
B14: CMP Amount | C14: =C13*C12 -> 1235.97
B15: Redemption | C15: 70704
B16: Valuation Date | C16: 45858
B17: Time to Maturity | C17: =(YEARFRAC(C16,C15,))*2 -> 136.05
B18: Coupon | C18: =7.38%/2 -> 0.0369
B19: Coupon Amount | C19: =(C18*C12) -> 36.9
B20: YTM | C20: =RATE(C17,C19,-C14,C12,) -> 0.029747845
B21: YTM (Annualised) | C21: =C20*2 -> 0.05949569
B24: Notes -
A25: # | B25: 1. Tax rate taken according to KPMG Corporate Tax Rate Table

Sheet Cost of Equity
A2: # | B2: Calculation of Cost of Equity (CAPM)
B5: Risk free rate of returns 1 | C5: 0.04416
B7: Date 2 | C7: Year | D7: Index Value
B8: 31048 | C8: 1985 | D8: 179.63
B9: 45857 | C9: 2025 | D9: 6296.79
B10: Total Years | C10: =YEARFRAC(B8,B9) -> 40.55
B12: CAGR | C12: =(D9/D8)^(1/C10)-1 -> 0.091678372
B13: Bottom up Beta | C13: =F29 -> 0.44407787
B14: Cost of Equity (Ke) | C14: =C5+(C12-C5)*C13 -> 0.065261857
B17: Name | C17: Regression Beta | D17: Market Cap | E17: Net Debt | F17: Total Capital | G17: Unlevered Beta
B18: Target Firm
B19: Coca Cola | C19: =H36 -> 0.42653283 | D19: 268203 | E19: 29951 | F19: =SUM(D19:E19) -> 298154 | G19: =C19/(1+((E19*(1-Valuation!$D$5))/D19)) -> 0.39438232
B21: Comps -
B22: PepsiCo, Inc. | C22: =K36 -> 0.37732384 | D22: 212201 | E22: 35040 | F22: =SUM(D22:E22) -> 247241 | G22: =C22/(1+((E22*(1-Valuation!$D$5))/D22)) -> 0.33673323
B23: Monster Beverage Corporation | C23: =N36 -> 0.56391026 | D23: 51116 | E23: 0 | F23: =SUM(D23:E23) -> 51116 | G23: =C23/(1+((E23*(1-Valuation!$D$5))/D23)) -> 0.56391026
B24: KEURIG DR PEPPER INC | C24: =Q36 -> 0.414647 | D24: 43569 | E24: 15044 | F24: =SUM(D24:E24) -> 58613 | G24: =C24/(1+((E24*(1-Valuation!$D$5))/D24)) -> 0.33117111
F25: Average Unlevered Beta | G25: =AVERAGE(G22:G24) -> 0.41060487
B27: Relevered Beta -
B28: Average Unlevered Beta of Comps | C28: Market Cap | D28: Net Debt | E28: Total Capital | F28: Relevered Beta
B29: =G25 -> 0.41060487 | C29: =D19 -> 268203 | D29: =E19 -> 29951 | E29: =F19 -> 298154 | F29: =B29*(1+((D29*(1-Valuation!D5)/'Cost of Equity'!C29))) -> 0.44407787
B31: Notes -
B32: 1. Risk free return taken as the 10 year US treasury yield
A33: # | B33: 2. Valuation date is on 19-07-2025
E35: S&P 500 | H35: Coca Cola | K35: PepsiCo, Inc. | N35: Monster Beverage Corporation | Q35: KEURIG DR PEPPER INC
B36: Regression Beta | E36: =SLOPE(F38:F297,$F$38:$F$297) -> 1 | H36: =SLOPE(I38:I297,$F$38:$F$297) -> 0.42653283 | K36: =SLOPE(L38:L297,$F$38:$F$297) -> 0.37732384 | N36: =SLOPE(O38:O297,$F$38:$F$297) -> 0.56391026 | Q36: =SLOPE(R38:R297,$F$38:$F$297) -> 0.414647
C37: Date | E37: Price | F37: Returns | H37: Price | I37: Returns | K37: Price | L37: Returns | N37: Price | O37: Returns | Q37: Price | R37: Returns
C38: 07/13/2025 | E38: 6296.79 | F38: =E38/E39-1 -> 0.0059171692 | H38: 69.85 | I38: =H38/H39-1 -> -0.00028624589 | K38: 143.27 | L38: =K38/K39-1 -> 0.059219281 | N38: 59 | O38: =N38/N39-1 -> 0.0028896821 | Q38: 33.54 | R38: =Q38/Q39-1 -> 0.001492983
C39: 45815 | E39: 6259.75 | F39: =E39/E40-1 -> -0.0031213422 | H39: 69.87 | I39: =H39/H40-1 -> -0.020742817 | K39: 135.26 | L39: =K39/K40-1 -> -0.00088639385 | N39: 58.83 | O39: =N39/N40-1 -> -0.067374762 | Q39: 33.49 | R39: =Q39/Q40-1 -> -0.0088783664
C40: 06/29/2025 | E40: 6279.35 | F40: =E40/E41-1 -> 0.017216717 | H40: 71.35 | I40: =H40/H41-1 -> 0.014503057 | K40: 135.38 | L40: =K40/K41-1 -> 0.033119658 | N40: 63.08 | O40: =N40/N41-1 -> 0.022200616 | Q40: 33.79 | R40: =Q40/Q41-1 -> 0.028614916
C41: 06/22/2025 | E41: 6173.07 | F41: =E41/E42-1 -> 0.034389327 | H41: 70.33 | I41: =H41/H42-1 -> 0.021644393 | K41: 131.04 | L41: =K41/K42-1 -> 0.015263036 | N41: 61.71 | O41: =N41/N42-1 -> -0.021873514 | Q41: 32.85 | R41: =Q41/Q42-1 -> -0.02173913
C42: 06/15/2025 | E42: 5967.84 | F42: =E42/E43-1 -> -0.0015275298 | H42: 68.84 | I42: =H42/H43-1 -> -0.030695579 | K42: 129.07 | L42: =K42/K43-1 -> -0.013603363 | N42: 63.09 | O42: =N42/N43-1 -> 0.00047573739 | Q42: 33.58 | R42: =Q42/Q43-1 -> 0.016959419
C43: 45875 | E43: 5976.97 | F43: =E43/E44-1 -> -0.0038980994 | H43: 71.02 | I43: =H43/H44-1 -> -0.0046250876 | K43: 130.85 | L43: =K43/K44-1 -> 0.006306237 | N43: 63.06 | O43: =N43/N44-1 -> -0.0055196341 | Q43: 33.02 | R43: =Q43/Q44-1 -> 0.0076289289
C44: 45663 | E44: 6000.36 | F44: =E44/E45-1 -> 0.014999095 | H44: 71.35 | I44: =H44/H45-1 -> -0.010402219 | K44: 130.03 | L44: =K44/K45-1 -> -0.010802587 | N44: 63.41 | O44: =N44/N45-1 -> -0.008444097 | Q44: 32.77 | R44: =Q44/Q45-1 -> -0.026730027
C45: 05/25/2025 | E45: 5911.69 | F45: =E45/E46-1 -> 0.018761568 | H45: 72.1 | I45: =H45/H46-1 -> 0.0045980215 | K45: 131.45 | L45: =K45/K46-1 -> 0.016313592 | N45: 63.95 | O45: =N45/N46-1 -> 0.0093118687 | Q45: 33.67 | R45: =Q45/Q46-1 -> 0.022782503
C46: 05/18/2025 | E46: 5802.82 | F46: =E46/E47-1 -> -0.026107768 | H46: 71.77 | I46: =H46/H47-1 -> -0.0031944444 | K46: 129.34 | L46: =K46/K47-1 -> -0.020003031 | N46: 63.36 | O46: =N46/N47-1 -> 0.0079541839 | Q46: 32.92 | R46: =Q46/Q47-1 -> -0.026611473
C47: 45966 | E47: 5958.38 | F47: =E47/E48-1 -> 0.052734054 | H47: 72 | I47: =H47/H48-1 -> 0.020986954 | K47: 131.98 | L47: =K47/K48-1 -> 0.011806194 | N47: 62.86 | O47: =N47/N48-1 -> 0.030491803 | Q47: 33.82 | R47: =Q47/Q48-1 -> 0.0083482409
C48: 45752 | E48: 5659.91 | F48: =E48/E49-1 -> -0.0047057417 | H48: 70.52 | I48: =H48/H49-1 -> -0.01577111 | K48: 130.44 | L48: =K48/K49-1 -> -0.024747664 | N48: 61 | O48: =N48/N49-1 -> 0.01582015 | Q48: 33.54 | R48: =Q48/Q49-1 -> -0.025283348
C49: 04/27/2025 | E49: 5686.67 | F49: =E49/E50-1 -> 0.029222419 | H49: 71.65 | I49: =H49/H50-1 -> -0.0036156306 | K49: 133.75 | L49: =K49/K50-1 -> 0.0027740291 | N49: 60.05 | O49: =N49/N50-1 -> 0.023521391 | Q49: 34.41 | R49: =Q49/Q50-1 -> 0.00029069767
C50: 04/20/2025 | E50: 5525.21 | F50: =E50/E51-1 -> 0.045906449 | H50: 71.91 | I50: =H50/H51-1 -> -0.014931507 | K50: 133.38 | L50: =K50/K51-1 -> -0.066227947 | N50: 58.67 | O50: =N50/N51-1 -> 0.0044512926 | Q50: 34.4 | R50: =Q50/Q51-1 -> -0.028248588
C51: 04/13/2025 | E51: 5282.7 | F51: =E51/E52-1 -> -0.01503908 | H51: 73 | I51: =H51/H52-1 -> 0.02197956 | K51: 142.84 | L51: =K51/K52-1 -> -0.011008793 | N51: 58.41 | O51: =N51/N52-1 -> 0.0044711952 | Q51: 35.4 | R51: =Q51/Q52-1 -> 0.0068259386
C52: 45812 | E52: 5363.36 | F52: =E52/E53-1 -> 0.05701132 | H52: 71.43 | I52: =H52/H53-1 -> 0.021450021 | K52: 144.43 | L52: =K52/K53-1 -> -0.014869381 | N52: 58.15 | O52: =N52/N53-1 -> 0.01874562 | Q52: 35.16 | R52: =Q52/Q53-1 -> 0.039929015
C53: 03/30/2025 | E53: 5074.08 | F53: =E53/E54-1 -> -0.090819826 | H53: 69.93 | I53: =H53/H54-1 -> -0.0062526645 | K53: 146.61 | L53: =K53/K54-1 -> -0.017820058 | N53: 57.08 | O53: =N53/N54-1 -> -0.013480816 | Q53: 33.81 | R53: =Q53/Q54-1 -> 0.0020746888
C54: 03/23/2025 | E54: 5580.94 | F54: =E54/E55-1 -> -0.015283473 | H54: 70.37 | I54: =H54/H55-1 -> 0.02475608 | K54: 149.27 | L54: =K54/K55-1 -> 0.026263321 | N54: 57.86 | O54: =N54/N55-1 -> 0.009596929 | Q54: 33.74 | R54: =Q54/Q55-1 -> 0.0056631893
C55: 03/16/2025 | E55: 5667.56 | F55: =E55/E56-1 -> 0.005075422 | H55: 68.67 | I55: =H55/H56-1 -> -0.0070850202 | K55: 145.45 | L55: =K55/K56-1 -> -0.021131974 | N55: 57.31 | O55: =N55/N56-1 -> 0.040297695 | Q55: 33.55 | R55: =Q55/Q56-1 -> -0.0011908306
C56: 45903 | E56: 5638.94 | F56: =E56/E57-1 -> -0.022747912 | H56: 69.16 | I56: =H56/H57-1 -> -0.031779364 | K56: 148.59 | L56: =K56/K57-1 -> -0.037878788 | N56: 55.09 | O56: =N56/N57-1 -> 0.00036317414 | Q56: 33.59 | R56: =Q56/Q57-1 -> 0.0074985003
C57: 45691 | E57: 5770.2 | F57: =E57/E58-1 -> -0.030951381 | H57: 71.43 | I57: =H57/H58-1 -> 0.0030894537 | K57: 154.44 | L57: =K57/K58-1 -> 0.0063204535 | N57: 55.07 | O57: =N57/N58-1 -> 0.0076852699 | Q57: 33.34 | R57: =Q57/Q58-1 -> -0.0053699284
C58: 02/23/2025 | E58: 5954.5 | F58: =E58/E59-1 -> -0.0097503297 | H58: 71.21 | I58: =H58/H59-1 -> -0.0019621584 | K58: 153.47 | L58: =K58/K59-1 -> -0.00019543974 | N58: 54.65 | O58: =N58/N59-1 -> 0.031132075 | Q58: 33.52 | R58: =Q58/Q59-1 -> -0.015276146
C59: 02/16/2025 | E59: 6013.13 | F59: =E59/E60-1 -> -0.016599533 | H59: 71.35 | I59: =H59/H60-1 -> 0.036009874 | K59: 153.5 | L59: =K59/K60-1 -> 0.070507009 | N59: 53 | O59: =N59/N60-1 -> 0.076142132 | Q59: 34.04 | R59: =Q59/Q60-1 -> 0.075513428
C60: 45902 | E60: 6114.63 | F60: =E60/E61-1 -> 0.014709616 | H60: 68.87 | I60: =H60/H61-1 -> 0.078790727 | K60: 143.39 | L60: =K60/K61-1 -> -0.0082307373 | N60: 49.25 | O60: =N60/N61-1 -> 0.057547778 | Q60: 31.65 | R60: =Q60/Q61-1 -> 0.019652062
C61: 45690 | E61: 6025.99 | F61: =E61/E62-1 -> -0.0024070736 | H61: 63.84 | I61: =H61/H62-1 -> 0.0056710775 | K61: 144.58 | L61: =K61/K62-1 -> -0.040546818 | N61: 46.57 | O61: =N61/N62-1 -> -0.043933484 | Q61: 31.04 | R61: =Q61/Q62-1 -> -0.033021807
C62: 01/26/2025 | E62: 6040.53 | F62: =E62/E63-1 -> -0.0099504363 | H62: 63.48 | I62: =H62/H63-1 -> 0.025193798 | K62: 150.69 | L62: =K62/K63-1 -> 0.010528433 | N62: 48.71 | O62: =N62/N63-1 -> 0.0089063795 | Q62: 32.1 | R62: =Q62/Q63-1 -> 0.030497592
C63: 01/19/2025 | E63: 6101.24 | F63: =E63/E64-1 -> 0.017439708 | H63: 61.92 | I63: =H63/H64-1 -> -0.012597672 | K63: 149.12 | L63: =K63/K64-1 -> 0.0058684654 | N63: 48.28 | O63: =N63/N64-1 -> -0.023067584 | Q63: 31.15 | R63: =Q63/Q64-1 -> -0.01486401
C64: 45992 | E64: 5996.66 | F64: =E64/E65-1 -> 0.029109119 | H64: 62.71 | I64: =H64/H65-1 -> 0.026854429 | K64: 148.25 | L64: =K64/K65-1 -> 0.039329781 | N64: 49.42 | O64: =N64/N65-1 -> -0.006433454 | Q64: 31.62 | R64: =Q64/Q65-1 -> 0.040816327
C65: 45778 | E65: 5827.04 | F65: =E65/E66-1 -> -0.019424583 | H65: 61.07 | I65: =H65/H66-1 -> -0.011012146 | K65: 142.64 | L65: =K65/K66-1 -> -0.046842633 | N65: 49.74 | O65: =N65/N66-1 -> -0.050582172 | Q65: 30.38 | R65: =Q65/Q66-1 -> -0.036778694
C66: 12/29/2024 | E66: 5942.47 | F66: =E66/E67-1 -> -0.0047514253 | H66: 61.75 | I66: =H66/H67-1 -> -0.011208967 | K66: 149.65 | L66: =K66/K67-1 -> -0.021191706 | N66: 52.39 | O66: =N66/N67-1 -> -0.0030447193 | Q66: 31.54 | R66: =Q66/Q67-1 -> -0.02262163
C67: 12/22/2024 | E67: 5970.84 | F67: =E67/E68-1 -> 0.0067427097 | H67: 62.45 | I67: =H67/H68-1 -> -0.001598721 | K67: 152.89 | L67: =K67/K68-1 -> 0.0006544931 | N67: 52.55 | O67: =N67/N68-1 -> 0.016047951 | Q67: 32.27 | R67: =Q67/Q68-1 -> -0.0030892802
C68: 12/15/2024 | E68: 5930.85 | F68: =E68/E69-1 -> -0.0198708 | H68: 62.55 | I68: =H68/H69-1 -> -0.0090304183 | K68: 152.79 | L68: =K68/K69-1 -> -0.032791036 | N68: 51.72 | O68: =N68/N69-1 -> -0.019711903 | Q68: 32.37 | R68: =Q68/Q69-1 -> -0.035171386
C69: 45516 | E69: 6051.09 | F69: =E69/E70-1 -> -0.0064332123 | H69: 63.12 | I69: =H69/H70-1 -> 0.009435471 | K69: 157.97 | L69: =K69/K70-1 -> 0.0011407567 | N69: 52.76 | O69: =N69/N70-1 -> 0.0093744021 | Q69: 33.55 | R69: =Q69/Q70-1 -> 0.025366748
C70: 45303 | E70: 6090.27 | F70: =E70/E71-1 -> 0.009596544 | H70: 62.53 | I70: =H70/H71-1 -> -0.024188514 | K70: 157.79 | L70: =K70/K71-1 -> -0.034628327 | N70: 52.27 | O70: =N70/N71-1 -> -0.051877381 | Q70: 32.72 | R70: =Q70/Q71-1 -> 0.002143951
C71: 11/24/2024 | E71: 6032.38 | F71: =E71/E72-1 -> 0.010560631 | H71: 64.08 | I71: =H71/H72-1 -> 0.0025031289 | K71: 163.45 | L71: =K71/K72-1 -> 0.0089506173 | N71: 55.13 | O71: =N71/N72-1 -> 0.019792823 | Q71: 32.65 | R71: =Q71/Q72-1 -> -0.00030618494
C72: 11/17/2024 | E72: 5969.34 | F72: =E72/E73-1 -> 0.016815941 | H72: 63.92 | I72: =H72/H73-1 -> 0.035309362 | K72: 162 | L72: =K72/K73-1 -> 0.021308788 | N72: 54.06 | O72: =N72/N73-1 -> 0.039615385 | Q72: 32.66 | R72: =Q72/Q73-1 -> 0.031585597
C73: 45576 | E73: 5870.62 | F73: =E73/E74-1 -> -0.020835488 | H73: 61.74 | I73: =H73/H74-1 -> -0.034105131 | K73: 158.62 | L73: =K73/K74-1 -> -0.039307129 | N73: 52 | O73: =N73/N74-1 -> -0.039527152 | Q73: 31.66 | R73: =Q73/Q74-1 -> -0.037104623
C74: 45362 | E74: 5995.54 | F74: =E74/E75-1 -> 0.046561234 | H74: 63.92 | I74: =H74/H75-1 -> -0.016766651 | K74: 165.11 | L74: =K74/K75-1 -> -0.0028987258 | N74: 54.14 | O74: =N74/N75-1 -> 0.035181644 | Q74: 32.88 | R74: =Q74/Q75-1 -> 0.0018281536
C75: 10/27/2024 | E75: 5728.8 | F75: =E75/E76-1 -> -0.013656743 | H75: 65.01 | I75: =H75/H76-1 -> -0.028541542 | K75: 165.59 | L75: =K75/K76-1 -> -0.036090576 | N75: 52.3 | O75: =N75/N76-1 -> -0.020048717 | Q75: 32.82 | R75: =Q75/Q76-1 -> -0.050896472
C76: 10/20/2024 | E76: 5808.12 | F76: =E76/E77-1 -> -0.0096424863 | H76: 66.92 | I76: =H76/H77-1 -> -0.049971607 | K76: 171.79 | L76: =K76/K77-1 -> -0.01867931 | N76: 53.37 | O76: =N76/N77-1 -> -0.012580944 | Q76: 34.58 | R76: =Q76/Q77-1 -> -0.063887385
C77: 10/13/2024 | E77: 5864.67 | F77: =E77/E78-1 -> 0.0085364994 | H77: 70.44 | I77: =H77/H78-1 -> 0.01250539 | K77: 175.06 | L77: =K77/K78-1 -> 0.0014301241 | N77: 54.05 | O77: =N77/N78-1 -> 0.053400897 | Q77: 36.94 | R77: =Q77/Q78-1 -> 0.015393073
C78: 45453 | E78: 5815.03 | F78: =E78/E79-1 -> 0.011121409 | H78: 69.57 | I78: =H78/H79-1 -> -0.0085506627 | K78: 174.81 | L78: =K78/K79-1 -> 0.040721557 | N78: 51.31 | O78: =N78/N79-1 -> 0.0070657507 | Q78: 36.38 | R78: =Q78/Q79-1 -> -0.00027480077
C79: 09/29/2024 | E79: 5751.07 | F79: =E79/E80-1 -> 0.0022481035 | H79: 70.17 | I79: =H79/H80-1 -> -0.022565817 | K79: 167.97 | L79: =K79/K80-1 -> -0.011941176 | N79: 50.95 | O79: =N79/N80-1 -> -0.028783835 | Q79: 36.39 | R79: =Q79/Q80-1 -> -0.027525387
C80: 09/22/2024 | E80: 5738.17 | F80: =E80/E81-1 -> 0.0062463284 | H80: 71.79 | I80: =H80/H81-1 -> 0.0020938023 | K80: 170 | L80: =K80/K81-1 -> -0.0068933287 | N80: 52.46 | O80: =N80/N81-1 -> 0.025009769 | Q80: 37.42 | R80: =Q80/Q81-1 -> -0.0010678057
C81: 09/15/2024 | E81: 5702.55 | F81: =E81/E82-1 -> 0.013602867 | H81: 71.64 | I81: =H81/H82-1 -> 0.0032208374 | K81: 171.18 | L81: =K81/K82-1 -> -0.034844384 | N81: 51.18 | O81: =N81/N82-1 -> 0.0068856974 | Q81: 37.46 | R81: =Q81/Q82-1 -> -0.003988301
C82: 45513 | E82: 5626.02 | F82: =E82/E83-1 -> 0.040233562 | H82: 71.41 | I82: =H82/H83-1 -> 0.0037953331 | K82: 177.36 | L82: =K82/K83-1 -> 0.00011277772 | N82: 50.83 | O82: =N82/N83-1 -> 0.044809866 | Q82: 37.61 | R82: =Q82/Q83-1 -> 0.02034726
C83: 45300 | E83: 5408.42 | F83: =E83/E84-1 -> -0.042486368 | H83: 71.14 | I83: =H83/H84-1 -> -0.018352422 | K83: 177.34 | L83: =K83/K84-1 -> 0.025798242 | N83: 48.65 | O83: =N83/N84-1 -> 0.03225122 | Q83: 36.86 | R83: =Q83/Q84-1 -> 0.0068287353
C84: 08/25/2024 | E84: 5648.4 | F84: =E84/E85-1 -> 0.0024473744 | H84: 72.47 | I84: =H84/H85-1 -> 0.038400917 | K84: 172.88 | L84: =K84/K85-1 -> -0.017001194 | N84: 47.13 | O84: =N84/N85-1 -> 0.010289389 | Q84: 36.61 | R84: =Q84/Q85-1 -> 0.024629163
C85: 08/18/2024 | E85: 5634.61 | F85: =E85/E86-1 -> 0.0144682 | H85: 69.79 | I85: =H85/H86-1 -> 0.0088175773 | K85: 175.87 | L85: =K85/K86-1 -> 0.018827482 | N85: 46.65 | O85: =N85/N86-1 -> -0.0019255456 | Q85: 35.73 | R85: =Q85/Q86-1 -> 0.0096072337
C86: 45604 | E86: 5554.25 | F86: =E86/E87-1 -> 0.039312071 | H86: 69.18 | I86: =H86/H87-1 -> 0.0072801398 | K86: 172.62 | L86: =K86/K87-1 -> 0.0013341841 | N86: 46.74 | O86: =N86/N87-1 -> 0.014763352 | Q86: 35.39 | R86: =Q86/Q87-1 -> 0.024016204
C87: 45390 | E87: 5344.16 | F87: =E87/E88-1 -> -0.00044888676 | H87: 68.68 | I87: =H87/H88-1 -> -0.0093754507 | K87: 172.39 | L87: =K87/K88-1 -> -0.031734442 | N87: 46.06 | O87: =N87/N88-1 -> -0.1075373 | Q87: 34.56 | R87: =Q87/Q88-1 -> -0.014542344
C88: 07/28/2024 | E88: 5346.56 | F88: =E88/E89-1 -> -0.02061512 | H88: 69.33 | I88: =H88/H89-1 -> 0.034004474 | K88: 178.04 | L88: =K88/K89-1 -> 0.030622287 | N88: 51.61 | O88: =N88/N89-1 -> 0.011960784 | Q88: 35.07 | R88: =Q88/Q89-1 -> 0.039419087
C89: 07/21/2024 | E89: 5459.1 | F89: =E89/E90-1 -> -0.0083378747 | H89: 67.05 | I89: =H89/H90-1 -> 0.026956655 | K89: 172.75 | L89: =K89/K90-1 -> 0.020016533 | N89: 51 | O89: =N89/N90-1 -> 0.0021615249 | Q89: 33.74 | R89: =Q89/Q90-1 -> 0.023044269
C90: 07/14/2024 | E90: 5505 | F90: =E90/E91-1 -> -0.019651491 | H90: 65.29 | I90: =H90/H91-1 -> 0.024960754 | K90: 169.36 | L90: =K90/K91-1 -> 0.017910807 | N90: 50.89 | O90: =N90/N91-1 -> 0.0011804053 | Q90: 32.98 | R90: =Q90/Q91-1 -> 0.011036174
C91: 45480 | E91: 5615.35 | F91: =E91/E92-1 -> 0.0086506837 | H91: 63.7 | I91: =H91/H92-1 -> -0.00094102886 | K91: 166.38 | L91: =K91/K92-1 -> 0.012105359 | N91: 50.83 | O91: =N91/N92-1 -> 0.021708543 | Q91: 32.62 | R91: =Q91/Q92-1 -> -0.0012247397
C92: 06/30/2024 | E92: 5567.19 | F92: =E92/E93-1 -> 0.019542238 | H92: 63.76 | I92: =H92/H93-1 -> 0.0017282011 | K92: 164.39 | L92: =K92/K93-1 -> -0.0032741163 | N92: 49.75 | O92: =N92/N93-1 -> -0.004004004 | Q92: 32.66 | R92: =Q92/Q93-1 -> -0.022155689
C93: 06/23/2024 | E93: 5460.48 | F93: =E93/E94-1 -> -0.00075760071 | H93: 63.65 | I93: =H93/H94-1 -> 0.014019436 | K93: 164.93 | L93: =K93/K94-1 -> -0.014048302 | N93: 49.95 | O93: =N93/N94-1 -> 0.017518843 | Q93: 33.4 | R93: =Q93/Q94-1 -> -0.028504945
C94: 06/16/2024 | E94: 5464.62 | F94: =E94/E95-1 -> 0.00607924 | H94: 62.77 | I94: =H94/H95-1 -> 0.0035171863 | K94: 167.28 | L94: =K94/K95-1 -> 0.021183078 | N94: 49.09 | O94: =N94/N95-1 -> 0.02206954 | Q94: 34.38 | R94: =Q94/Q95-1 -> 0.0099882491
C95: 45541 | E95: 5431.6 | F95: =E95/E96-1 -> 0.015823856 | H95: 62.55 | I95: =H95/H96-1 -> -0.021279925 | K95: 163.81 | L95: =K95/K96-1 -> -0.042270814 | N95: 48.03 | O95: =N95/N96-1 -> -0.08844183 | Q95: 34.04 | R95: =Q95/Q96-1 -> -0.017037251
C96: 45328 | E96: 5346.99 | F96: =E96/E97-1 -> 0.0131653 | H96: 63.91 | I96: =H96/H97-1 -> 0.015572859 | K96: 171.04 | L96: =K96/K97-1 -> -0.010757663 | N96: 52.69 | O96: =N96/N97-1 -> 0.014830508 | Q96: 34.63 | R96: =Q96/Q97-1 -> 0.011094891
C97: 05/26/2024 | E97: 5277.51 | F97: =E97/E98-1 -> -0.0051293942 | H97: 62.93 | I97: =H97/H98-1 -> 0.015 | K97: 172.9 | L97: =K97/K98-1 -> -0.028597112 | N97: 51.92 | O97: =N97/N98-1 -> -0.014800759 | Q97: 34.25 | R97: =Q97/Q98-1 -> 0.0017548991
C98: 05/19/2024 | E98: 5304.72 | F98: =E98/E99-1 -> 0.00027341621 | H98: 62 | I98: =H98/H99-1 -> -0.016341425 | K98: 177.99 | L98: =K98/K99-1 -> -0.023052857 | N98: 52.7 | O98: =N98/N99-1 -> -0.02605803 | Q98: 34.19 | R98: =Q98/Q99-1 -> 0.013037037
C99: 45631 | E99: 5303.27 | F99: =E99/E100-1 -> 0.015430775 | H99: 63.03 | I99: =H99/H100-1 -> -0.0036357888 | K99: 182.19 | L99: =K99/K100-1 -> 0.013348907 | N99: 54.11 | O99: =N99/N100-1 -> -0.024341868 | Q99: 33.75 | R99: =Q99/Q100-1 -> -0.0082280341
C100: 45417 | E100: 5222.68 | F100: =E100/E101-1 -> 0.018505048 | H100: 63.26 | I100: =H100/H101-1 -> 0.017532572 | K100: 179.79 | L100: =K100/K101-1 -> 0.020664207 | N100: 55.46 | O100: =N100/N101-1 -> 0.0083636364 | Q100: 34.03 | R100: =Q100/Q101-1 -> 0.0059119125
C101: 04/28/2024 | E101: 5127.79 | F101: =E101/E102-1 -> 0.0054569055 | H101: 62.17 | I101: =H101/H102-1 -> 0.0069646906 | K101: 176.15 | L101: =K101/K102-1 -> 0.0032463834 | N101: 55 | O101: =N101/N102-1 -> 0.030541503 | Q101: 33.83 | R101: =Q101/Q102-1 -> 0.003262159
C102: 04/21/2024 | E102: 5099.96 | F102: =E102/E103-1 -> 0.02672113 | H102: 61.74 | I102: =H102/H103-1 -> 0.026092737 | K102: 175.58 | L102: =K102/K103-1 -> 0.0083271119 | N102: 53.37 | O102: =N102/N103-1 -> 0.0043281897 | Q102: 33.72 | R102: =Q102/Q103-1 -> 0.07047619
C103: 04/14/2024 | E103: 4967.23 | F103: =E103/E104-1 -> -0.030483604 | H103: 60.17 | I103: =H103/H104-1 -> 0.03242965 | K103: 174.13 | L103: =K103/K104-1 -> 0.035871505 | N103: 53.14 | O103: =N103/N104-1 -> -0.033993819 | Q103: 31.5 | R103: =Q103/Q104-1 -> 0.042356056
C104: 45477 | E104: 5123.41 | F104: =E104/E105-1 -> -0.015550483 | H104: 58.28 | I104: =H104/H105-1 -> -0.020668795 | K104: 168.1 | L104: =K104/K105-1 -> -0.0061487525 | N104: 55.01 | O104: =N104/N105-1 -> -0.015921288 | Q104: 30.22 | R104: =Q104/Q105-1 -> -0.017874553
C105: 03/31/2024 | E105: 5204.34 | F105: =E105/E106-1 -> -0.0095178281 | H105: 59.51 | I105: =H105/H106-1 -> -0.027296502 | K105: 169.14 | L105: =K105/K106-1 -> -0.033540941 | N105: 55.9 | O105: =N105/N106-1 -> -0.057017544 | Q105: 30.77 | R105: =Q105/Q106-1 -> 0.0032605152
C106: 03/24/2024 | E106: 5254.35 | F106: =E106/E107-1 -> 0.0038535167 | H106: 61.18 | I106: =H106/H107-1 -> 0.011406844 | K106: 175.01 | L106: =K106/K107-1 -> 0.0173817 | N106: 59.28 | O106: =N106/N107-1 -> -0.003697479 | Q106: 30.67 | R106: =Q106/Q107-1 -> 0.029194631
C107: 03/17/2024 | E107: 5234.18 | F107: =E107/E108-1 -> 0.022882146 | H107: 60.49 | I107: =H107/H108-1 -> 0.010187041 | K107: 172.02 | L107: =K107/K108-1 -> 0.044698166 | N107: 59.5 | O107: =N107/N108-1 -> -0.015715467 | Q107: 29.8 | R107: =Q107/Q108-1 -> 0.031855956
C108: 45568 | E108: 5117.09 | F108: =E108/E109-1 -> -0.0012881341 | H108: 59.88 | I108: =H108/H109-1 -> 0.0060483871 | K108: 164.66 | L108: =K108/K109-1 -> 0.0098742717 | N108: 60.45 | O108: =N108/N109-1 -> 0.021459953 | Q108: 28.88 | R108: =Q108/Q109-1 -> -0.0089224434
C109: 45354 | E109: 5123.69 | F109: =E109/E110-1 -> -0.0026065391 | H109: 59.52 | I109: =H109/H110-1 -> -0.00016798253 | K109: 163.05 | L109: =K109/K110-1 -> -0.009356583 | N109: 59.18 | O109: =N109/N110-1 -> 0.0066337813 | Q109: 29.14 | R109: =Q109/Q110-1 -> -0.0047814208
C110: 02/25/2024 | E110: 5137.08 | F110: =E110/E111-1 -> 0.009487502 | H110: 59.53 | I110: =H110/H111-1 -> -0.027287582 | K110: 164.59 | L110: =K110/K111-1 -> -0.029540094 | N110: 58.79 | O110: =N110/N111-1 -> 0.063302586 | Q110: 29.28 | R110: =Q110/Q111-1 -> -0.030142431
C111: 02/18/2024 | E111: 5088.8 | F111: =E111/E112-1 -> 0.016627477 | H111: 61.2 | I111: =H111/H112-1 -> 0.030476511 | K111: 169.6 | L111: =K111/K112-1 -> 0.01972102 | N111: 55.29 | O111: =N111/N112-1 -> 0.0049073064 | Q111: 30.19 | R111: =Q111/Q112-1 -> -0.025185664
...

Sheet DCF>

Sheet Valuation
A2: # | B2: Particulars | C2: Unit | D2: Forecast
D3: 2025 | E3: =D3+1 -> 2026 | F3: =E3+1 -> 2027 | G3: =F3+1 -> 2028 | H3: =G3+1 -> 2029
B4: EBIT | D4: ='P&L'!H22 -> 15012.967 | E4: ='P&L'!I22 -> 16406.574 | F4: ='P&L'!J22 -> 17857.633 | G4: ='P&L'!K22 -> 19432.805 | H4: ='P&L'!L22 -> 21068.247
B5: Tax Rate 1 | D5: 0.27 | E5: =D5 -> 0.27 | F5: =E5 -> 0.27 | G5: =F5 -> 0.27 | H5: =G5 -> 0.27
B6: Less: Incomes Taxes | D6: =D5*D4 -> 4053.5012 | E6: =E5*E4 -> 4429.7751 | F6: =F5*F4 -> 4821.5608 | G6: =G5*G4 -> 5246.8574 | H6: =H5*H4 -> 5688.4267
B7: NOPAT | D7: =D4-D6 -> 10959.466 | E7: =E4-E6 -> 11976.799 | F7: =F4-F6 -> 13036.072 | G7: =G4-G6 -> 14185.948 | H7: =H4-H6 -> 15379.82
B8: Add: D&A | D8: =CapEx!H19 -> 1130.8021 | E8: =CapEx!I19 -> 1161.1629 | F8: =CapEx!J19 -> 1203.3066 | G8: =CapEx!K19 -> 1241.4044 | H8: =CapEx!L19 -> 1287.1522
B9: Changes in WC | D9: =SUM(CFS!D17:D21) -> -2949.7271 | E9: =SUM(CFS!E17:E21) -> 969.12126 | F9: =SUM(CFS!F17:F21) -> 1042.1069 | G9: =SUM(CFS!G17:G21) -> 1134.7923 | H9: =SUM(CFS!H17:H21) -> 1197.1288
B10: Less: CapEx | D10: =CapEx!H7 -> 832.49001 | E10: =CapEx!I7 -> 814.54187 | F10: =CapEx!J7 -> 810.3691 | G10: =CapEx!K7 -> 886.39859 | H10: =CapEx!L7 -> 879.67146
B11: FCFF | D11: =D7+D8+D9-D10 -> 8308.0513 | E11: =E7+E8+E9-E10 -> 13292.542 | F11: =F7+F8+F9-F10 -> 14471.116 | G11: =G7+G8+G9-G10 -> 15675.746 | H11: =H7+H8+H9-H10 -> 16984.43
B13: Terminal Value | H13: =(H11*(1+D17))/($D$18-$D$17) -> 497876.46
B14: Total Cash Flow | D14: =D11 -> 8308.0513 | E14: =E11 -> 13292.542 | F14: =F11 -> 14471.116 | G14: =G11 -> 15675.746 | H14: =H11+H13 -> 514860.89
B15: Mid Year Convention | D15: 0.5 | E15: =D15+1 -> 1.5 | F15: =E15+1 -> 2.5 | G15: =F15+1 -> 3.5 | H15: =G15+1 -> 4.5
B16: PV of Cashflows | D16: =D14/((1+$D$18)^D15) -> 8057.8366 | E16: =E14/((1+$D$18)^E15) -> 12127.349 | F16: =F14/((1+$D$18)^F15) -> 12419.339 | G16: =G14/((1+$D$18)^G15) -> 12655.031 | H16: =H14/((1+$D$18)^H15) -> 390988.05
B17: GDP Growth (US) | D17: 0.028
B18: WACC | D18: ='Cost of Equity'!C14*('Cost of Equity'!D19/'Cost of Equity'!F19)+'Cost of Debt'!C8*('Cost of Equity'!E19/'Cost of Equity'!F19) -> 0.063068929 | H18: WACC
B19: Value of Firm | D19: =SUM(D16:H16) -> 436247.61 | H19: GDP Growth (US) | I19: =D25 -> 98.264262 | J19: 0.043 | K19: 0.053 | L19: 0.06307 | M19: 0.073 | N19: 0.083
B20: Less: Value of debt | D20: =SUM('Balance Sheet'!G25:G26,'Balance Sheet'!G29) -> 44522 | I20: 0.008 | J20: 105.13965 | K20: 80.896931 | L20: 65.392657 | M20: 54.817024 | N20: 47.004317
B21: Add:Cash and cash equivalents | D21: =SUM('Balance Sheet'!G6:G7) -> 12848 | I21: 0.018 | J21: 143.91575 | K21: 101.73164 | L21: 78.180523 | M21: 63.410961 | N21: 53.105204
B22: Add: Investments | D22: =SUM('Balance Sheet'!G9,'Balance Sheet'!G14,'Balance Sheet'!G41) -> 19928 | I22: 0.028 | J22: 234.39331 | K22: 139.23411 | L22: 98.261155 | M22: 75.824425 | N22: 61.424596
B23: Value of Equity | D23: =D19-D20+D21+D22 -> 424501.61 | I23: 0.038 | J23: 686.78111 | K23: 226.73987 | L23: 134.36144 | M23: 95.331297 | N23: 73.441495
B24: Shares Outstanding | D24: ='P&L'!G49 -> 4320 | I24: 0.04 | J24: 1139.1689 | K24: 260.39593 | L24: 145.33705 | M24: 100.65135 | N24: 76.515586
B25: FV/Share | D25: =D23/D24 -> 98.264262
B27: Notes -
B28: 1. Tax rate taken according to KPMG Corporate Tax Rate Table
